Workbook
Name _PL03: [1]CIPA!#REF!
Name __PL03: #REF!
Name _PL01: #REF!
Name Serviço: #REF!
Name Desculpas: #REF!
Name TLV: #REF!
Name _PL04: #REF!
Name servico: #REF!
Name Desculpas: #REF!
Name __PL03: #REF!
Name serviços: #REF!
Name _PL02: #REF!
Name TLV: #REF!
Name __PL03: #REF!
Name __PL04: #REF!
Name _PL02: #REF!
Name serviços.: #REF!
Name TLV: 'TLV _Andrea'!$A$1:$J$6
Name __PL03: #REF!
Name serviços: #REF!
Name serviços: #REF!
Name serviços.: #REF!
Name _PL02: #REF!
Name __PL02: #REF!
Name Serviço: #REF!
Name TLV: #REF!
Name ___PL03: #REF!
Name DadosExternos_1: 'Lista de Empresa'!$A$1:$C$1052
Name siglas: #REF!
Name _PL01: #REF!
Name _PL02: #REF!
Name Serviço: #REF!
Name TLV: TLV!$C$2:$I$7
Name _PL04: #REF!
Name Desculpas: #REF!
Name _PL01: #REF!
Name servico: #REF!
Name siglas: 'TLV _Andrea'!$A$12:$F$16
Name _PL01: #REF!
Name siglas: #REF!
Name siglas: #REF!
Name servico: #REF!
Name _PL04: #REF!
Name TLV: TLV!$C$2:$I$7
Name _PL04: #REF!
Name serviços.: #REF!
Name __PL01: #REF!

Sheet Capa 
K6: Nº Relatório | L6: 0000-1/2026.0 | T6: 0000 - | U6: 1 / 2026.0
L7: (Nº DA AMOSTRA) | T7: =$T$6 -> 0000 - | U7: 2 / 2026.0
T8: =$T$6 -> 0000 - | U8: 3 / 2026.0
T9: =$T$6 -> 0000 - | U9: 4 / 2026.0
T10: =$T$6 -> 0000 - | U10: 5 / 2026.0
K11: Data de Assinatura (Entrega do Relatório): | M11: Exemplo: | T11: =$T$6 -> 0000 - | U11: 6 / 2026.0
M12: 01 de janeiro de 2026. | T12: =$T$6 -> 0000 - | U12: 7 / 2026.0
T13: =$T$6 -> 0000 - | U13: 8 / 2026.0
T14: =$T$6 -> 0000 - | U14: 9 / 2026.0
T15: =$T$6 -> 0000 - | U15: 10 / 2026.0
T16: =$T$6 -> 0000 - | U16: 11 / 2026.0
T17: =$T$6 -> 0000 - | U17: 12 / 2026.0
K18: Empresa: | L18: 11342 Sociedade Fogas Ltda - Manaus | T18: =$T$6 -> 0000 - | U18: 13 / 2026.0
K19: Endereço: | L19: =VLOOKUP($L$18,'Lista de Empresa'!A:C,3,FALSE) -> Rua Rio Quixito, 86 - Vila Buriti Manaus/Amazonas | T19: =$T$6 -> 0000 - | U19: 14 / 2026.0
K20: CNPJ: | L20: =IF(ISERROR(VLOOKUP(L18,'Lista de Empresa'!A:B,2,FALSE)),"", IF(OR(ISNUMBER(FIND(".",VLOOKUP(L18,'Lista de Empresa'!A:B,2,FALSE))), ISNUMBER(FIND("-",VLOOKUP(L18,'Lista de Empresa'!A:B,2,FALSE))), ISNUMBER(FIND("/",VLOOKUP(L18,'Lista de Empresa'!A:B,2,FALSE)))), VLOOKUP(L18,'Lista de Empresa'!A:B,2,FALSE), IF(LEN(VLOOKUP(L18,'Lista de Empresa'!A:B,2,FALSE))=11, TEXT(VLOOKUP(L18,'Lista de Empresa'!A:B,2,FALSE),"000\.000\.000\-00"), TEXT(VLOOKUP(L18,'Lista de Empresa'!A:B,2,FALSE),"00\.000\.000\/0000\-00") ) ) ) -> 04.563.672/0001-66 | T20: =$T$6 -> 0000 - | U20: 15 / 2026.0
T21: =$T$6 -> 0000 - | U21: 16 / 2026.0
T22: =$T$6 -> 0000 - | U22: 17 / 2026.0
T23: =$T$6 -> 0000 - | U23: 18 / 2026.0
T24: =$T$6 -> 0000 - | U24: 19 / 2026.0
T25: =$T$6 -> 0000 - | U25: 20 / 2026.0
C28: CNPJ:
K34: Data: | L34: Mês de 2026

Sheet Doc Base
A2: 1. Objetivo
A41: 2. Abreviaturas Utilizadas
A97: ANEXO - RELATÓRIOS ANALÍTICOS

Sheet Hidrocarbonetos Aromáticos
A1: Relatório de Ensaio Analítico N. | E1: {='Capa '!T6:U6} -> 0000 - | F1: 1 / 2026.0
A2: Folha 01 de 02
A3: Dados do Cliente
A4: Razão Social: | B4: ='Capa '!L18 -> 11342 Sociedade Fogas Ltda - Manaus
A5: Endereço: | B5: ='Capa '!L19 -> Rua Rio Quixito, 86 - Vila Buriti Manaus/Amazonas
A6: Serviço: | B6: Monitoramentos de Agentes Químicos no Ambiente de Trabalho
A7: Informações do Colaborador (a)
A8: Colaborador (a):
A9: Função: | E9: Matrícula:
A10: Local da Coleta: | E10: Setor:
A11: Informações Técnicas de Amostragem
A12: Data da Avaliação: | D12: Volume de Ar Amostrado: | F12: =#REF! -> #REF! | G12: L
A13: Jornada de Tabalho: 44 Horas/Semanais | D13: Resp. pela coleta:
A15: Resultados das Análises dos Agentes Químicos
A16: Agente Químico Código e-Social | B16: Valor Encontrado | C16: Unidade | D16: ACGIH | F16: NR 15 | G16: Bases de Efeitos Críticos
D17: TWA | E17: STEL
A18: Benzeno | B18: =VLOOKUP(A18,TLV!H:P,9,FALSE) -> < 0,011 | C18: =VLOOKUP(A18,TLV!B:D,3,FALSE) -> ppm | D18: =VLOOKUP(A18,TLV!B:G,4,FALSE) -> 0.02 | E18: =VLOOKUP(A18,TLV!B:G,5,FALSE) -> - | F18: =VLOOKUP(A18,TLV!B:G,6,FALSE) -> - | G18: =VLOOKUP(A18,TLV!$H:$I,2,FALSE) -> Síndrome mielodisplásica; Leucemia mieolóide aguda; Leucemia; Efeitos hematológicos; Dano cromossômico
A19: =VLOOKUP($A$18,TLV!H:L,4,FALSE) -> Método NIOSH 1501
A20: =VLOOKUP(A18,TLV!B:C,2,FALSE) -> Cód. e-Social: 01.03.001
A21: Tolueno | B21: =VLOOKUP(A21,TLV!H:P,9,FALSE) -> < 0,003 | C21: =VLOOKUP(A21,TLV!B:D,3,FALSE) -> ppm | D21: =VLOOKUP(A21,TLV!B:G,4,FALSE) -> 20 | E21: =VLOOKUP(A21,TLV!B:G,5,FALSE) -> - | F21: =VLOOKUP(A21,TLV!B:G,6,FALSE) -> 78 | G21: =VLOOKUP(A21,TLV!$H:$I,2,FALSE) -> Danos no sistema nervoso central; Danos auditivos; Comprometimento da visão; Dano reprodutivo feminino; Aborto
A22: =VLOOKUP($A$21,TLV!H:L,4,FALSE) -> Método NIOSH 1501
A23: =VLOOKUP(A21,TLV!B:C,2,FALSE) -> Cód. e-Social: 01.03.001
A24: Xileno | B24: =VLOOKUP(A24,TLV!H:P,9,FALSE) -> < 0,003 | C24: =VLOOKUP(A24,TLV!B:D,3,FALSE) -> ppm | D24: =VLOOKUP(A24,TLV!B:G,4,FALSE) -> 20 | E24: =VLOOKUP(A24,TLV!B:G,5,FALSE) -> - | F24: =VLOOKUP(A24,TLV!B:G,6,FALSE) -> 78 | G24: =VLOOKUP(A24,TLV!$H:$I,2,FALSE) -> Irritações no TRS; Irritações nos olhos; Efeitos hematológicos; Ototoxicidade - apenas para o para-xileno e misturas contendo para-xileno; Comprometimento do SNC
A25: =VLOOKUP($A$24,TLV!H:L,4,FALSE) -> Método NIOSH 1501
A26: =VLOOKUP(A24,TLV!B:C,2,FALSE) -> Cód. e-Social: 01.03.001
A27: Cumeno | B27: =VLOOKUP(A27,TLV!H:P,9,FALSE) -> < 0,007 | C27: =VLOOKUP(A27,TLV!B:D,3,FALSE) -> ppm | D27: =VLOOKUP(A27,TLV!B:G,4,FALSE) -> 5 | E27: =VLOOKUP(A27,TLV!B:G,5,FALSE) -> - | F27: =VLOOKUP(A27,TLV!B:G,6,FALSE) -> 39 | G27: =VLOOKUP(A27,TLV!$H:$I,2,FALSE) -> Adenoma TRS; efeito neurológico
A28: =VLOOKUP($A$27,TLV!H:L,4,FALSE) -> Método NIOSH 1501
A29: =VLOOKUP(A27,TLV!B:C,2,FALSE) -> Cód. e-Social: 01.03.001
A30: Estireno | B30: =VLOOKUP(A30,TLV!H:P,9,FALSE) -> < 0,004 | C30: =VLOOKUP(A30,TLV!B:D,3,FALSE) -> ppm | D30: =VLOOKUP(A30,TLV!B:G,4,FALSE) -> 10 | E30: =VLOOKUP(A30,TLV!B:G,5,FALSE) -> 20 | F30: =VLOOKUP(A30,TLV!B:G,6,FALSE) -> 78 | G30: =VLOOKUP(A30,TLV!$H:$I,2,FALSE) -> Comprometimento do SNC; Comprometimento do sistema auditivo; Irritações no TRS; Neuropatia periférica; Desordens visuais
A31: =VLOOKUP($A$27,TLV!H:L,4,FALSE) -> Método NIOSH 1501
A32: =VLOOKUP(A30,TLV!B:C,2,FALSE) -> Cód. e-Social: 01.03.002
A33: Etilbenzeno | B33: =VLOOKUP(A33,TLV!H:P,9,FALSE) -> < 0,001 | C33: =VLOOKUP(A33,TLV!B:D,3,FALSE) -> ppm | D33: =VLOOKUP(A33,TLV!B:G,4,FALSE) -> 20 | E33: =VLOOKUP(A33,TLV!B:G,5,FALSE) -> - | F33: =VLOOKUP(A33,TLV!B:G,6,FALSE) -> 78 | G33: =VLOOKUP(A33,TLV!$H:$I,2,FALSE) -> Irritações no TRS; Irritações nos olhos; Danos nos rins (nefrotoxicidade); Comprometimento do SNC; Ototoxicidade
A34: =VLOOKUP($A$27,TLV!H:L,4,FALSE) -> Método NIOSH 1501
A35: =VLOOKUP(A33,TLV!B:C,2,FALSE) -> Cód. e-Social: 01.19.035
A36: Viniltolueno | B36: =VLOOKUP(A36,TLV!H:P,9,FALSE) -> < 0,003 | C36: =VLOOKUP(A36,TLV!B:D,3,FALSE) -> ppm | D36: =VLOOKUP(A36,TLV!B:G,4,FALSE) -> 10 | E36: =VLOOKUP(A36,TLV!B:G,5,FALSE) -> - | F36: =VLOOKUP(A36,TLV!B:G,6,FALSE) -> - | G36: =VLOOKUP(A36,TLV!$H:$I,2,FALSE) -> Danos TRS e pulmão
A37: =VLOOKUP($A$27,TLV!H:L,4,FALSE) -> Método NIOSH 1501
A38: =VLOOKUP(A36,TLV!B:C,2,FALSE) -> Cód. e-Social: N. C.
A39: α Metil Estireno | B39: =VLOOKUP(A39,TLV!H:P,9,FALSE) -> < 0,003 | C39: =VLOOKUP(A39,TLV!B:D,3,FALSE) -> ppm | D39: =VLOOKUP(A39,TLV!B:G,4,FALSE) -> 10 | E39: =VLOOKUP(A39,TLV!B:G,5,FALSE) -> - | F39: =VLOOKUP(A39,TLV!B:G,6,FALSE) -> - | G39: =VLOOKUP(A39,TLV!$H:$I,2,FALSE) -> Irritações no TRS; Danos nos rins; Dano reprodutivo feminino
A40: =VLOOKUP($A$27,TLV!H:L,4,FALSE) -> Método NIOSH 1501
A41: =VLOOKUP(A39,TLV!B:C,2,FALSE) -> Cód. e-Social: 01.03.001
A42: Relatório de Ensaio Analítico N. | E42: =E1 -> 0000 - | F42: =F1 -> 1 / 2026.0
A43: Folha 02 de 02
A45: Legenda:
A46: TLV - TWA: Threshold Limits Values (Limite de Exposição) - Média Ponderada pelo Tempo.
A47: TLV - STEL: Threshold Limits Values (Limite de Exposição) - Exposição de Curta Duração.
A48: N.C.: Não Codificado pelo e-Social.
A49: N.D.: Nada Detectado
A51: Notas:
A52: Foram utilizados os dados fornecidos pelo interessado. O resultado de cada parâmetro está em função do volume de ar amostrado.
A53: Equipamento Utilizado na Coleta: Bomba Gravimétrica. Os resultados são válidos exclusivamente para a amostra analisada.
A54: Códigos retirados da "Tabela 24: Agentes Nocivos e Atividades - Aposentadoria Especial" do eSocial Versão S-1.0 de 2021.
A57: Tipo de Amostrador:
A58: =VLOOKUP($A$18,TLV!H:L,3,FALSE) -> Tubo de Carvão Ativado
A60: Metodologia de Análise: | C60: 1
A61: =VLOOKUP($A$18,TLV!H:L,5,FALSE) -> Cromatografia
A63: Referência:
A64: Valores Limites de Exposição TLV-TWA da American Conference of Governmental Industrial Hygienists - ACGIH.
A65: Norma Regulamentadora - NR 15.
A66: Ministério do Trabalho e Emprego - MTE.
A67: Nacional Institute for Occupational Safety and Health - NIOSH (Instituto Nacional de Segurança e Saúde Ocupacional).
A68: Occupational Safety and Health Administration - OSHA.
A70: Conclusão:
A71: De acordo com os resultados encontrados é possível afirmar que as concentrações dos agentes monitorados, encontram-se dentro dos limites exigidos pelas referências acima, índices esses também aceitos pela Associação Brasileira de Higienistas Ocupacionais - ABHO e Ministério do Trabalho e Emprego.
C76: Manaus, | D76: ='Capa '!M12 -> 01 de janeiro de 2026.

Sheet Var. Metais
A1: Relatório de Ensaio Analítico N. | E1: {='Capa '!T6:U6} -> 0000 - | F1: 1 / 2026.0
A2: Folha 01 de 03
A3: Dados do Cliente
A4: Razão Social: | B4: ='Capa '!L18 -> 11342 Sociedade Fogas Ltda - Manaus
A5: Endereço: | B5: ='Capa '!L19 -> Rua Rio Quixito, 86 - Vila Buriti Manaus/Amazonas
A6: Serviço: | B6: Monitoramento de Agentes Químicos no Ambiente de Trabalho | I6: Hora Final | J6: 0.5
A7: Informações do Colaborador (a) | I7: Hora Inicial | J7: 0.33333333
A8: Colaborador (a): | J8: =J6-J7 -> 0.16666667
A9: Função: | E9: Matrícula: | J9: =HOUR(J8)*60+MINUTE(J8) -> 240 | K9: min
A10: Local da Coleta: | E10: Setor: | I10: Vazão: | J10: 0.02 | K10: min/L
A11: Informações Técnicas de Amostragem | I11: Volume: | J11: =J10*J9 -> 4.8 | K11: L
A12: Data da Avaliação: | B12: 45471 | D12: Volume de Ar Amostrado: | F12: =$J$11 -> 4.8 | G12: L
A13: Jornada de Tabalho: 44 Horas/Semanais | D13: Resp. pela coleta: | F13: Willian Douglas Brito
A15: Resultado da Análise do Agente Químico
A16: Agente Químico Código e-Social | B16: Valor | C16: Unidade | D16: ACGIH | F16: NR 15 | G16: Bases de Efeitos Críticos
B17: Encontrado | D17: TWA | E17: STEL
A18: Alumínio | B18: =VLOOKUP(A18,TLV!H:P,9,FALSE) -> < 0,005 | C18: =VLOOKUP(A18,TLV!B:D,3,FALSE) -> mg/m3 | D18: =VLOOKUP(A18,TLV!B:G,4,FALSE) -> 1 | E18: =VLOOKUP(A18,TLV!B:G,5,FALSE) -> - | F18: =VLOOKUP(A18,TLV!B:G,6,FALSE) -> - | G18: =VLOOKUP(A18,TLV!$H:$I,2,FALSE) -> Pneumoconiose; Irritação TRI neurotoxicidade
A19: =VLOOKUP(A18,TLV!H:L,4,FALSE) -> Método NIOSH 7303
A20: =VLOOKUP(A18,TLV!B:C,2,FALSE) -> Cód. e-Social: N. C.
A21: Antimônio | B21: =VLOOKUP(A21,TLV!H:P,9,FALSE) -> < 0,005 | C21: =VLOOKUP(A21,TLV!B:D,3,FALSE) -> mg/m3 | D21: =VLOOKUP(A21,TLV!B:G,4,FALSE) -> 0.5 | E21: =VLOOKUP(A21,TLV!B:G,5,FALSE) -> - | F21: =VLOOKUP(A21,TLV!B:G,6,FALSE) -> - | G21: =VLOOKUP(A21,TLV!$H:$I,2,FALSE) -> Irritações na pele; Irritações no TRS
A22: =VLOOKUP(A21,TLV!H:L,4,FALSE) -> Método NIOSH 7303
A23: =VLOOKUP(A21,TLV!B:C,2,FALSE) -> Cód. e-Social: N. C.
A24: Arsênio | B24: =VLOOKUP(A24,TLV!H:P,9,FALSE) -> < 0,005 | C24: =VLOOKUP(A24,TLV!B:D,3,FALSE) -> mg/m3 | D24: =VLOOKUP(A24,TLV!B:G,4,FALSE) -> 0.01 | E24: =VLOOKUP(A24,TLV!B:G,5,FALSE) -> - | F24: =VLOOKUP(A24,TLV!B:G,6,FALSE) -> - | G24: =VLOOKUP(A24,TLV!$H:$I,2,FALSE) -> Câncer do pulmão
A25: =VLOOKUP(A24,TLV!H:L,4,FALSE) -> Método NIOSH 7303
A26: =VLOOKUP(A24,TLV!B:C,2,FALSE) -> Cód. e-Social: 01.01.001
A27: Bário | B27: =VLOOKUP(A27,TLV!H:P,9,FALSE) -> < 0,001 | C27: =VLOOKUP(A27,TLV!B:D,3,FALSE) -> mg/m3 | D27: =VLOOKUP(A27,TLV!B:G,4,FALSE) -> 0.5 | E27: =VLOOKUP(A27,TLV!B:G,5,FALSE) -> - | F27: =VLOOKUP(A27,TLV!B:G,6,FALSE) -> - | G27: =VLOOKUP(A27,TLV!$H:$I,2,FALSE) -> Irritação olhos, pele e GI; estim muscular
A28: =VLOOKUP(A27,TLV!H:L,4,FALSE) -> Método NIOSH 7303
A29: =VLOOKUP(A27,TLV!B:C,2,FALSE) -> Cód. e-Social: N. C.
A30: Cádmio | B30: =VLOOKUP(A30,TLV!H:P,9,FALSE) -> < 0,001 | C30: =VLOOKUP(A30,TLV!B:D,3,FALSE) -> mg/m3 | D30: =VLOOKUP(A30,TLV!B:G,4,FALSE) -> 0.002 | E30: =VLOOKUP(A30,TLV!B:G,5,FALSE) -> - | F30: =VLOOKUP(A30,TLV!B:G,6,FALSE) -> - | G30: =VLOOKUP(A30,TLV!$H:$I,2,FALSE) -> Dano rins
A31: =VLOOKUP(A30,TLV!H:L,4,FALSE) -> Método NIOSH 7303
A32: =VLOOKUP(A30,TLV!B:C,2,FALSE) -> Cód. e-Social: 01.06.001
A33: Chumbo | B33: =VLOOKUP(A33,TLV!H:P,9,FALSE) -> < 0,001 | C33: =VLOOKUP(A33,TLV!B:D,3,FALSE) -> mg/m3 | D33: =VLOOKUP(A33,TLV!B:G,4,FALSE) -> 0.05 | E33: =VLOOKUP(A33,TLV!B:G,5,FALSE) -> - | F33: =VLOOKUP(A33,TLV!B:G,6,FALSE) -> 0.1 | G33: =VLOOKUP(A33,TLV!$H:$I,2,FALSE) -> Comprometimento do SNC; Comprometimento do sistema nervoso periférico; Efeitos hematológicos
A34: =VLOOKUP(A33,TLV!H:L,4,FALSE) -> Método NIOSH 7303
A35: =VLOOKUP(A33,TLV!B:C,2,FALSE) -> Cód. e-Social: 01.08.001
A36: Cobalto | B36: =VLOOKUP(A36,TLV!H:P,9,FALSE) -> < 0,005 | C36: =VLOOKUP(A36,TLV!B:D,3,FALSE) -> mg/m3 | D36: =VLOOKUP(A36,TLV!B:G,4,FALSE) -> 0.02 | E36: =VLOOKUP(A36,TLV!B:G,5,FALSE) -> - | F36: =VLOOKUP(A36,TLV!B:G,6,FALSE) -> - | G36: =VLOOKUP(A36,TLV!$H:$I,2,FALSE) -> Mudanças na função pulmonar.
A37: =VLOOKUP(A36,TLV!H:L,4,FALSE) -> Método NIOSH 7303
A38: =VLOOKUP(A36,TLV!B:C,2,FALSE) -> Cód. e-Social: N. C.
A39: Cobre | B39: =VLOOKUP(A39,TLV!H:P,9,FALSE) -> < 0,005 | C39: =VLOOKUP(A39,TLV!B:D,3,FALSE) -> mg/m3 | D39: =VLOOKUP(A39,TLV!B:G,4,FALSE) -> 1 | E39: =VLOOKUP(A39,TLV!B:G,5,FALSE) -> - | F39: =VLOOKUP(A39,TLV!B:G,6,FALSE) -> - | G39: =VLOOKUP(A39,TLV!$H:$I,2,FALSE) -> Irritação; GI; febre dos fumos metálicos
A40: =VLOOKUP(A39,TLV!H:L,4,FALSE) -> Método NIOSH 7303
A41: =VLOOKUP(A39,TLV!B:C,2,FALSE) -> Cód. e-Social: N. C.
A42: Relatório de Ensaio Analítico N. | E42: {=ANCHORARRAY(E1)} -> #NAME?
A43: Folha 02 de 03
A45: Resultado da Análise do Agente Químico
A46: Agente Químico Código e-Social | B46: Valor | C46: Unidade | D46: ACGIH | F46: NR 15 | G46: Bases de Efeitos Críticos
B47: Encontrado | D47: TWA | E47: STEL
A48: Cromo | B48: =VLOOKUP(A48,TLV!H:P,9,FALSE) -> < 0,02 | C48: =VLOOKUP(A48,TLV!B:D,3,FALSE) -> mg/m3 | D48: =VLOOKUP(A48,TLV!B:G,4,FALSE) -> 0.5 | E48: =VLOOKUP(A48,TLV!B:G,5,FALSE) -> - | F48: =VLOOKUP(A48,TLV!B:G,6,FALSE) -> - | G48: =VLOOKUP(A48,TLV!$H:$I,2,FALSE) -> Irritações no TRS
A49: =VLOOKUP(A48,TLV!H:L,4,FALSE) -> Método NIOSH 7303
A50: =VLOOKUP(A48,TLV!B:C,2,FALSE) -> Cód. e-Social: 01.10.001
A51: Dióxido de Titânio | B51: =VLOOKUP(A51,TLV!H:P,9,FALSE) -> < 0,017 | C51: =VLOOKUP(A51,TLV!B:D,3,FALSE) -> mg/m3 | D51: =VLOOKUP(A51,TLV!B:G,4,FALSE) -> 2.5 | E51: =VLOOKUP(A51,TLV!B:G,5,FALSE) -> - | F51: =VLOOKUP(A51,TLV!B:G,6,FALSE) -> - | G51: =VLOOKUP(A51,TLV!$H:$I,2,FALSE) -> Irritação no TRI, Pneumoconiose
A52: =VLOOKUP(A51,TLV!H:L,4,FALSE) -> Método NIOSH 7303
A53: =VLOOKUP(A51,TLV!B:C,2,FALSE) -> Cód. e-Social: N. C.
A54: Estanho | B54: =VLOOKUP(A54,TLV!H:P,9,FALSE) -> < 0,001 | C54: =VLOOKUP(A54,TLV!B:D,3,FALSE) -> mg/m3 | D54: =VLOOKUP(A54,TLV!B:G,4,FALSE) -> 2 | E54: =VLOOKUP(A54,TLV!B:G,5,FALSE) -> - | F54: =VLOOKUP(A54,TLV!B:G,6,FALSE) -> - | G54: =VLOOKUP(A54,TLV!$H:$I,2,FALSE) -> Pneumoconiose
A55: =VLOOKUP(A54,TLV!H:L,4,FALSE) -> Método NIOSH 7303
A56: =VLOOKUP(A54,TLV!B:C,2,FALSE) -> Cód. e-Social: N. C.
A57: Ferro | B57: =VLOOKUP(A57,TLV!H:P,9,FALSE) -> < 0,005 | C57: =VLOOKUP(A57,TLV!B:D,3,FALSE) -> mg/m3 | D57: =VLOOKUP(A57,TLV!B:G,4,FALSE) -> 5 | E57: =VLOOKUP(A57,TLV!B:G,5,FALSE) -> - | F57: =VLOOKUP(A57,TLV!B:G,6,FALSE) -> - | G57: =VLOOKUP(A57,TLV!$H:$I,2,FALSE) -> Pneumoconiose
A58: =VLOOKUP(A57,TLV!H:L,4,FALSE) -> Método NIOSH 7303
A59: =VLOOKUP(A57,TLV!B:C,2,FALSE) -> Cód. e-Social: N. C.
A60: Hidróxido de Potássio | B60: =VLOOKUP(A60,TLV!H:P,9,FALSE) -> < 0,007 | C60: =VLOOKUP(A60,TLV!B:D,3,FALSE) -> mg/m3 | D60: =VLOOKUP(A60,TLV!B:G,4,FALSE) -> - | E60: =VLOOKUP(A60,TLV!B:G,5,FALSE) -> 2 | F60: =VLOOKUP(A60,TLV!B:G,6,FALSE) -> - | G60: =VLOOKUP(A60,TLV!$H:$I,2,FALSE) -> Irritação olhos, pele e TRS
A61: =VLOOKUP(A60,TLV!H:L,4,FALSE) -> Método NIOSH 7303
A62: =VLOOKUP(A60,TLV!B:C,2,FALSE) -> Cód. e-Social: N. C.
A63: Hidróxido de Sódio | B63: =VLOOKUP(A63,TLV!H:P,9,FALSE) -> < 0,008 | C63: =VLOOKUP(A63,TLV!B:D,3,FALSE) -> mg/m3 | D63: =VLOOKUP(A63,TLV!B:G,4,FALSE) -> - | E63: =VLOOKUP(A63,TLV!B:G,5,FALSE) -> 2 | F63: =VLOOKUP(A63,TLV!B:G,6,FALSE) -> - | G63: =VLOOKUP(A63,TLV!$H:$I,2,FALSE) -> Irritação olhos, pele e TRS
A64: =VLOOKUP(A63,TLV!H:L,4,FALSE) -> Método NIOSH 7303
A65: =VLOOKUP(A63,TLV!B:C,2,FALSE) -> Cód. e-Social: N. C.
A66: Manganês | B66: =VLOOKUP(A66,TLV!H:P,9,FALSE) -> < 0,005 | C66: =VLOOKUP(A66,TLV!B:D,3,FALSE) -> mg/m3 | D66: =VLOOKUP(A66,TLV!B:G,4,FALSE) -> 0.1 | E66: =VLOOKUP(A66,TLV!B:G,5,FALSE) -> - | F66: =VLOOKUP(A66,TLV!B:G,6,FALSE) -> 1 | G66: =VLOOKUP(A66,TLV!$H:$I,2,FALSE) -> Compr SNC
A67: =VLOOKUP(A66,TLV!H:L,4,FALSE) -> Método NIOSH 7303
A68: =VLOOKUP(A66,TLV!B:C,2,FALSE) -> Cód. e-Social: 01.14.001
A69: Óxido de Cálcio | B69: =VLOOKUP(A69,TLV!H:P,9,FALSE) -> < 0,012 | C69: =VLOOKUP(A69,TLV!B:D,3,FALSE) -> mg/m3 | D69: =VLOOKUP(A69,TLV!B:G,4,FALSE) -> 2 | E69: =VLOOKUP(A69,TLV!B:G,5,FALSE) -> - | F69: =VLOOKUP(A69,TLV!B:G,6,FALSE) -> - | G69: =VLOOKUP(A69,TLV!$H:$I,2,FALSE) -> Irritações no TRS
A70: =VLOOKUP(A69,TLV!H:L,4,FALSE) -> Método NIOSH 7303
A71: =VLOOKUP(A69,TLV!B:C,2,FALSE) -> Cód. e-Social: N. C.
A72: Óxido de Zinco | B72: =VLOOKUP(A72,TLV!H:P,9,FALSE) -> < 0,012 | C72: =VLOOKUP(A72,TLV!B:D,3,FALSE) -> mg/m3 | D72: =VLOOKUP(A72,TLV!B:G,4,FALSE) -> 2 | E72: =VLOOKUP(A72,TLV!B:G,5,FALSE) -> 10 | F72: =VLOOKUP(A72,TLV!B:G,6,FALSE) -> - | G72: =VLOOKUP(A72,TLV!$H:$I,2,FALSE) -> Febre de fumos metálicos
A73: =VLOOKUP(A72,TLV!H:L,4,FALSE) -> Método NIOSH 7303
A74: =VLOOKUP(A72,TLV!B:C,2,FALSE) -> Cód. e-Social: N. C.
A75: Tungstênio | B75: =VLOOKUP(A75,TLV!H:P,9,FALSE) -> 5 | C75: =VLOOKUP(A75,TLV!B:D,3,FALSE) -> mg/m3 | D75: =VLOOKUP(A75,TLV!B:G,4,FALSE) -> 3 | E75: =VLOOKUP(A75,TLV!B:G,5,FALSE) -> - | F75: =VLOOKUP(A75,TLV!B:G,6,FALSE) -> - | G75: =VLOOKUP(A75,TLV!$H:$I,2,FALSE) -> Dano pulmonar
A76: =VLOOKUP(A75,TLV!H:L,4,FALSE) -> Método NIOSH 7303
A77: =VLOOKUP(A75,TLV!B:C,2,FALSE) -> Cód. e-Social: N. C.
A78: Prata | B78: =VLOOKUP(A78,TLV!H:P,9,FALSE) -> < 0,001 | C78: =VLOOKUP(A78,TLV!B:D,3,FALSE) -> mg/m3 | D78: =VLOOKUP(A78,TLV!B:G,4,FALSE) -> 0.1 | E78: =VLOOKUP(A78,TLV!B:G,5,FALSE) -> - | F78: =VLOOKUP(A78,TLV!B:G,6,FALSE) -> - | G78: =VLOOKUP(A78,TLV!$H:$I,2,FALSE) -> Argíria
A79: =VLOOKUP(A78,TLV!H:L,4,FALSE) -> Método NIOSH 7303
A80: =VLOOKUP(A78,TLV!B:C,2,FALSE) -> Cód. e-Social: N. C.
A84: Relatório de Ensaio Analítico N. | E84: {=ANCHORARRAY(E1)} -> #NAME?
A85: Folha 03 de 03
A87: Legenda:
A88: TLV - TWA: Threshold Limits Values (Limite de Exposição) - Média Ponderada pelo Tempo.
A89: TLV - STEL: Threshold Limits Values (Limite de Exposição) - Exposição de Curta Duração.
A90: N.C.: Não Codificado pelo e-Social.
A92: Notas:
A93: Foram utilizados os dados fornecidos pelo interessado. O resultado de cada parâmetro está em função do volume de ar amostrado.
A94: O resultado é valido exclusivamente para a amostra analisada.
A95: O limite de Tolerância da ACGIH neste relatório foi corrigido através do Método Brief e Scala para jornada de trabalho de 44 horas/semanais.
A96: Códigos retirados da "Tabela 24: Agentes Nocivos e Atividades - Aposentadoria Especial" do eSocial Versão S-1.0 de 2021.
A98: Tipo de Amostrador:
A99: =VLOOKUP($A$18,TLV!H:L,3,FALSE) -> Filtro de éster de celulose
A101: Metodologia de Análise: | C101: 1
A102: =VLOOKUP($A$18,TLV!H:L,5,FALSE) -> Espectrofotometria
A104: Referência: | C104: 1
A105: Valores Limites de Exposição TLV-TWA da American Conference of Governmental Industrial Hygienists - ACGIH.
A106: Norma Regulamentadora - NR 15.
A107: Ministério do Trabalho e Emprego - MTE.
A108: Nacional Institute for Occupational Safety and Health - NIOSH (Instituto Nacional de Segurança e Saúde Ocupacional).
A109: Occupational Safety and Health Administration - OSHA.
A111: Conclusão:
...

Sheet Anexos
A25: ANEXO B - DOCUMENTOS E CERTIFICADOS DE CALIBRAÇÃO

Sheet TLV
B1: 1 | C1: 2 | D1: 3 | E1: 4 | F1: 5 | G1: 6 | H1: 1 | I1: 2 | J1: 3 | K1: 4 | L1: 5 | M1: 6 | N1: 7 | O1: 8 | P1: 9 | Q1: 10
A2: Grupos | B2: Agente | C2: e-Social | D2: Unidade | E2: TWA | F2: STEL | G2: NR 15 | H2: Agente | I2: Bases de Efeitos Críticos | J2: Amostrador/Filtro | K2: Método | L2: Método de Análise | M2: Vazão | N2: Volume | O2: L.Q | P2: Valor Encontrado | Q2: CAS
A3: VOC | B3: 1,1,2,2 Tetracloroetano | C3: Cód. e-Social: N. C. | D3: ppm | E3: 1 | F3: - | G3: 4 | H3: 1,1,2,2 Tetracloroetano | I3: Dano fígado | K3: Método NIOSH 2562 | L3: Cromatografia | M3: 0,02 - 0,2 | N3: 3 - 30 | Q3: 106-99-0
A4: VOC | B4: 1,3-Butadieno | C4: Cód. e-Social:01.19.003 | D4: ppm | E4: 2 | F4: - | G4: 780 | H4: 1,3-Butadieno | I4: Câncer | J4: Tubo de Carvão Ativado | K4: Método NIOSH 1024 | L4: Cromatografia | M4: 0,02 - 0,5 | N4: 5 - 25 | O4: < 0,004 | P4: < 0,004 | Q4: 111-76-2
A5: VOC | B5: 1-Methoxy-2-propanol | C5: Cód. e-Social: N. C. | D5: ppm | E5: 50 | F5: 100 | G5: - | H5: 1-Methoxy-2-propanol | I5: Irritações nos olhos; Irritações no TRS | J5: Tubo de Carvão Ativado | K5: OSHA 99 | L5: Cromatografia | M5: 0,1 - 0,2 | N5: 3 - 25 | O5: 2 | P5: 2 | Q5: 708-85-0
A6: VOC | B6: 2-Butoxietanol | C6: Cód. e-Social: N. C. | D6: ppm | E6: 20 | F6: - | G6: 39 | H6: 2-Butoxietanol | I6: Irritação olhos e TRS | J6: Tubo de Carvão Ativado | K6: Método NIOSH 1403 | L6: Cromatografia | M6: 0,02 - 0,2 | N6: 1 - 10 | O6: < 0,009 | P6: < 0,009 | Q6: 110-8-5
A7: VOC | B7: 2-Cianoacrilato de etila | C7: Cód. e-Social: N. C. | D7: ppm | E7: 0.2 | F7: 1 | G7: - | H7: 2-Cianoacrilato de etila | I7: Irritações nos olhos; Irritações TRS; Asma | J7: Tubo de Carvão Ativado | K7: Método OSHA 55 - HPLC | L7: Cromatografia | M7: 0,02 - 0,2 | N7: 1,5 - 12 | O7: <0,0005 | P7: < 0,0005 | Q7: 75-07-0
A8: ABC | B8: 2-Etoxietanol | C8: Cód. e-Social: N. C. | D8: ppm | E8: 5 | F8: - | G8: 78 | H8: 2-Etoxietanol | I8: Dano embrio/fetal; Dano reprodutivo masculino | J8: Tubo de Carvão Ativado | K8: Método NIOSH 1403 | L8: Cromatografia | M8: 0,02 - 0,05 | N8: 6 | O8: <0,007 | P8: < 0,007 | Q8: 112-07-2
A9: ABC | B9: 2-propanol | C9: Cód. e-Social: N. C. | D9: ppm | E9: 200 | F9: 400 | G9: 310 | H9: 2-propanol | I9: Irritações nos olhos; Irritações no trato respiratório superior; Comprometimento do sistema nervoso central | J9: Tubo de Carvão Ativado | K9: Método NIOSH 1400 | L9: Cromatografia | M9: 0,02 - 0,2 | N9: 0,2 - 3 | Q9: 111-15-9
A10: ABC | B10: Acetaldeído | C10: Cód. e-Social: N. C. | D10: ppm | E10: - | F10: 25 | G10: 78 | H10: Acetaldeído | I10: Irritações no trato respiratório superior; Irritações nos olhos | J10: Tubo de Sílica gel | K10: Método EPA 8315 | L10: Cromatografia | M10: 0,1 - 1,5 | N10: 15 | O10: < 0,001 | P10: < 0,001 | Q10: 111-15-9
A11: ABC | B11: Acetato de 2-Butóxietanol | C11: Cód. e-Social: N. C. | D11: ppm | E11: 20 | F11: - | G11: - | H11: Acetato de 2-Butóxietanol | I11: Hemólise | J11: Tubo de Carvão Ativado | K11: Método OSHA 83 | L11: Cromatografia | M11: 1 | N11: 48 | Q11: 141-78-6
B12: Acetato de 2-etoxietanol | C12: Cód. e-Social: N. C. | D12: ppm | E12: 5 | F12: - | G12: 78 | H12: Acetato de 2-etoxietanol | I12: Dano reprodutivo masculino | J12: Tubo de Carvão Ativado | K12: Método NIOSH 1450 | L12: Cromatografia | M12: 0,02 - 0,2 | N12: 1 - 10 | O12: <0,010 | P12: < 0,010 | Q12: 105-46-4
B13: Acetato de 2-etoxietila | C13: Cód. e-Social: N. C. | D13: ppm | E13: 5 | F13: - | G13: 78 | H13: Acetato de 2-etoxietila | I13: Dano reprodutivo masculino. | J13: Tubo de Carvão Ativado | K13: Método NIOSH 1450 | L13: Cromatografia | M13: 0,02 - 0,2 | N13: 1 - 10 | O13: < 0,002 | P13: < 0,002 | Q13: 108-21-4
B14: Acetato de 2-Metoxietila | C14: Cód. e-Social: N. C. | D14: ppm | E14: 0.1 | F14: - | G14: - | H14: Acetato de 2-Metoxietila | I14: Efe Hematológico e reprodutivo | J14: Tubo de Carvão Ativado | K14: Método NIOSH 1451 | L14: Cromatografia | M14: 0,02 - 0,2 | N14: 0,2 - 20 | Q14: 79-20-9
B15: Acetato de Butila | C15: Cód. e-Social: N. C. | D15: ppm | E15: 50 | F15: 150 | G15: - | H15: Acetato de Butila | I15: Irritação nos olhos e no TRS. | J15: Tubo de Carvão Ativado | K15: Método NIOSH 1450 | L15: Cromatografia | M15: 0,02 - 0,2 | N15: 1 - 10 | O15: < 0,010 | P15: < 0,010 | Q15: 110-49-6
B16: Acetato de etila | C16: Cód. e-Social: N. C. | D16: ppm | E16: 400 | F16: - | G16: 310 | H16: Acetato de etila | I16: Irritações no trato respiratório superior; Irritações nos olhos | J16: Tubo de Carvão Ativado | K16: Método NIOSH 1457 | L16: Cromatografia | M16: 0,02 - 0,2 | N16: 1 - 10 | O16: < 0,007 | P16: < 0,007 | Q16: 105-46-4
B17: Acetato de isobutila | C17: Cód. e-Social: N. C. | D17: ppm | E17: 50 | F17: 150 | G17: - | H17: Acetato de isobutila | I17: Irritação nos olhos e no TRS. | J17: Tubo de Carvão Ativado | K17: Método NIOSH 1450 | L17: Cromatografia | M17: 0,01 - 0,2 | N17: 1 - 10 | O17: < 0,002 | P17: < 0,002 | Q17: 123-86-4 | R17: Tempo: 360
B18: Acetato de isopropila | C18: Cód. e-Social: N. C. | D18: ppm | E18: 100 | F18: 150 | G18: - | H18: Acetato de isopropila | I18: Irritação nos olhos e pele. | J18: Tubo de Carvão Ativado | K18: Método NIOSH 1454 | L18: Cromatografia | M18: 0,02 - 0,2 | N18: 0,1 - 9 | O18: < 0,008 | P18: < 0,008 | Q18: 108-21-4
B19: Acetato de metila | C19: Cód. e-Social: N. C. | D19: ppm | E19: 200 | F19: 250 | G19: - | H19: Acetato de metila | I19: Dor de cabeça; Tontura; Náusea; Dano olhos (degeneração das células ganglionares da retina). | J19: Tubo de Carvão Ativado | K19: Método NIOSH 1458 | L19: Cromatografia | M19: 0,02 - 0,2 | N19: 0,2 - 10 | O19: < 0,007 | P19: < 0,007 | Q19: 107-98-2
B20: Acetato de n-butila | C20: Cód. e-Social: N. C. | D20: ppm | E20: 50 | F20: 150 | G20: - | H20: Acetato de n-butila | I20: Irritação nos olhos e no TRS. | J20: Tubo de Carvão Ativado | K20: Método NIOSH 1450 | L20: Cromatografia | M20: 0,02 - 0,2 | N20: 1 - 10 | Q20: 61-64-1
B21: Acetato de N-Propila | C21: Cód. e-Social: N. C. | D21: ppm | E21: 100 | F21: 150 | G21: - | H21: Acetato de N-Propila | I21: Irritações TRS; Irritações nos olhos; Comprometimento do SNC | J21: Tubo de Carvão Ativado | K21: Método NIOSH 1450 | L21: Cromatografia | M21: 0,01 - 0,2 | N21: 1 - 10 | Q21: 64-19-7
B22: Acetato de Vinila | C22: Cód. e-Social: N. C. | D22: ppm | E22: 10 | F22: 15 | G22: - | H22: Acetato de Vinila | I22: Irritação no TRS. | J22: Tubo de Carvão Ativado | K22: Método NIOSH 1453 | L22: Cromatografia | M22: 0,05 - 0,2 | N22: 1,5 - 24 | Q22: 7647-01-0
B23: Acetona | C23: Cód. e-Social: N. C. | D23: ppm | E23: 250 | F23: 500 | G23: 780 | H23: Acetona | I23: Comprometimento do SNC; Irritações noTRS; Irritações nos olhos | J23: Tubo de Carvão Ativado | K23: Método NIOSH 1300 | L23: Cromatografia | M23: 0,02 - 0,2 | N23: 0,5 - 3 | O23: < 0,008 | P23: < 0,008 | Q23: 7664-39-3
B24: Acetonitrila | C24: Cód. e-Social: N. C. | D24: ppm | E24: 20 | F24: - | G24: 30 | H24: Acetonitrila | I24: Irritação no TRI | J24: Tubo de Carvão Ativado | K24: Método NIOSH 1606 | L24: Cromatografia | M24: 0,02 - 0,2 | N24: 3 - 25 | Q24: 64-18-6
B25: Ácido acético | C25: Cód. e-Social: N. C. | D25: ppm | E25: 10 | F25: 15 | G25: 8 | H25: Ácido acético | I25: Comprometimento da função pulmonar; Irritações no trato respiratório superior; Irritações nos olhos | J25: Tubo de Carvão Ativado | K25: Método NIOSH 1603 | L25: Cromatografia | M25: 0,02 - 1 | N25: 20 - 300 | O25: < 0,002 | P25: < 0,002 | Q25: 7664-38-2
B26: Ácido Bórico - como Borato, compostos inogânicos | C26: Cód. e-Social: N. C. | D26: mg/m3 | E26: 2 | F26: 6 | G26: - | H26: Ácido Bórico - como Borato, compostos inogânicos | I26: Irritação TRS | J26: Filtro de éster de celulose | K26: Método NIOSH 7303 | L26: Espectrofotometria | M26: 1 - 4 | N26: 240 - 960 | Q26: 7697-37-2
B27: Ácido Carboxílico de Hidrogênio | C27: Cód. e-Social: N. C. | D27: ppm | E27: 5 | F27: - | G27: 4 | H27: Ácido Carboxílico de Hidrogênio | I27: Irritações no trato respiratório superior | J27: Tubo de Carvão Ativado | K27: Método NIOSH 2011 | L27: Cromatografia | M27: 0,05 - 0,2 | N27: 1 - 24 | Q27: 79-21-0
B28: Ácido clorídrico | C28: Cód. e-Social: 01.09.001 | D28: ppm | E28: - | F28: 2 | G28: 4 | H28: Ácido clorídrico | I28: Irritações no TRS | J28: Tubo de Sílica gel | K28: Método OSHA ID165-SG / OSHA ID-174-SG | L28: Cromatografia | M28: 2 | N28: 30 - 600 | O28: < 0,005 | P28: < 0,005 | Q28: 7664-93-9
B29: Ácido fluorídrico | C29: Cód. e-Social: N. C. | D29: ppm | E29: 0.5 | F29: 2 | G29: 2,5 | H29: Ácido fluorídrico | I29: Irritações no TRS; Irritações noTRI; Irritações na pele; Irritações nos olhos; Fluorese. | J29: Filtro de éster de celulose | K29: Método NIOSH 7902 | L29: Cromatografia | M29: 1 - 2 | N29: 15 - 1000 | O29: < 0,002 | P29: < 0,002 | Q29: 64-17-5
B30: Ácido fórmico | C30: Cód. e-Social: N. C. | D30: ppm | E30: 5 | F30: - | G30: 4 | H30: Ácido fórmico | I30: Irritações no TRS | J30: Tubo de Sílica gel | K30: Método NIOSH 2011 | L30: Cromatografia | M30: 0,05 - 0,2 | N30: 1 - 24 | O30: < 0,002 | P30: < 0,002 | Q30: 67-63-0
B31: Ácido fosfórico | C31: Cód. e-Social: 01.12.001 | D31: mg/m3 | E31: 1 | F31: 3 | G31: - | H31: Ácido fosfórico | I31: Irritações nos olhos; Irritações na pele; Irritações no trato respiratório superior | J31: Tubo de Sílica gel | K31: Método OSHA ID165-SG / OSHA ID-174-SG | L31: Cromatografia | M31: 1 - 5 | N31: 15 - 2000 | O31: < 0,005 | P31: < 0,005 | Q31: 107-13-1
B32: Ácido nítrico | C32: Cód. e-Social: N. C. | D32: ppm | E32: 2 | F32: 4 | G32: - | H32: Ácido nítrico | I32: Irritação olhos e TRS; corrosão dental | J32: Tubo de Sílica gel | K32: Método OSHA ID165-SG / OSHA ID-174-SG | L32: Cromatografia | M32: 2 | N32: 30 - 600 | O32: < 0,005 | P32: < 0,005 | Q32: 96-33-3
B33: Ácido peracético | C33: Cód. e-Social: N. C. | D33: ppm | E33: - | F33: 0.4 | G33: - | H33: Ácido peracético | I33: Irritação olhos, pele e TRS | J33: Tubo de Sílica gel | K33: Método IT 10-220 | L33: Cromatografia | M33: 1 | N33: 15 - 120 | O33: < 0,005 | P33: < 0,005 | Q33: 71-36-3
B34: Ácido Sulfúrico | C34: Cód. e-Social: N. C. | D34: mg/m3 | E34: 0.2 | F34: - | G34: - | H34: Ácido Sulfúrico | I34: Função pulmonar | J34: Filtro de éster de celulose | K34: Método OSHA ID-113 | L34: Cromatografia | M34: 1.6 | N34: 480 | O34: < 0,001 | P34: < 0,001 | Q34: 7429-90-5
B35: Acrilato de Etila | C35: Cód. e-Social: N. C. | D35: ppm | E35: 5 | F35: 15 | G35: - | H35: Acrilato de Etila | I35: Irritações gastrointestinal; Irritações no trato respiratório superior; Irritações nos olhos; Comprometimento do sistema nervoso central; Sensibilidade na pele | J35: Tubo de Carvão Ativado | K35: Método NIOSH 1450 | L35: Cromatografia | M35: 0,02 - 0,2 | N35: 1-10 | Q35: 12172-73-5
B36: Acrilato de Metila | D36: ppm | E36: 2 | G36: 8 | H36: Acrilato de Metila | I36: Irritações nos olhos; Irritações na pele; Irritações no trato respiratório superior; Danos nos olhos | J36: Tubo de Carvão Ativado | K36: Método NIOSH 1459 | L36: Espectrofotometria | M36: 0,02 - 0,2 | N36: 1 - 5 | O36: <0,004 | P36: < 0,004 | Q36: 7664-41-7
B37: Acrilonitrila | C37: Cód. e-Social: 01.19.002 | D37: ppm | E37: 2 | F37: - | G37: 16 | H37: Acrilonitrila | I37: Comprometimento do SNC; Irritações no TRI | J37: Tubo de Carvão Ativado | K37: Método NIOSH 1604 | L37: Espectrofotometria | M37: 0,02 - 0,2 | N37: 3,5 - 20 | O37: <0,002 | P37: < 0,002 | Q37: 7440-36-0
B38: Álcool Etílico | C38: Cód. e-Social: N. C. | D38: ppm | E38: - | F38: 1000 | G38: 780 | H38: Álcool Etílico | I38: Irritação TRS | J38: Tubo de Carvão Ativado | K38: Método NIOSH 1400 | L38: Cromatografia | M38: 0,02 - 0,05 | N38: 0,1 - 1 | O38: < 0,007 | P38: < 0,007 | Q38: 7440-38-2
B39: Álcool Isopropílico | C39: Cód. e-Social: N. C. | D39: ppm | E39: 200 | F39: 400 | G39: 310 | H39: Álcool Isopropílico | I39: Irritações nos olhos; Irritações noTRS; Comprometimento do SNC | J39: Tubo de Carvão Ativado | K39: Método NIOSH 1400 | L39: Cromatografia | M39: 0,02 - 0,2 | N39: 0,2 - 3 | O39: < 0,007 | P39: < 0,007 | Q39: 7440-39-3
B40: Álcool Metílico | C40: Cód. e-Social: N. C. | D40: ppm | E40: 200 | F40: 250 | G40: 156 | H40: Álcool Metílico | I40: Dor de Cabeça; Danos nos olhos; Tontura; Nausea | J40: Tubo de Carvão Ativado | K40: Método NIOSH 1400 | L40: Cromatografia | M40: 0,02 - 0,2 | N40: 1-5 | Q40: 71-43-2
B41: Álcool n-butílico | C41: Cód. e-Social: N. C. | D41: ppm | E41: 20 | F41: - | G41: 40 | H41: Álcool n-butílico | I41: Irritação olhos e TRS | J41: Tubo de Carvão Ativado | K41: Método NIOSH 1401 | L41: Cromatografia | M41: 0,02 - 0,2 | N41: 2 - 10 | Q41: 7440-41-7
B42: Alumínio | C42: Cód. e-Social: N. C. | D42: mg/m3 | E42: 1 | F42: - | G42: - | H42: Alumínio | I42: Pneumoconiose; Irritação TRI neurotoxicidade | J42: Filtro de éster de celulose | K42: Método NIOSH 7303 | L42: Espectrofotometria | M42: 1.7 | N42: 45 - 1000 | O42: < 0,005 | P42: < 0,005 | Q42: 1303-96-4
B43: Amianto | C43: Cód. e-Social: 01.02.001 | D43: f/cc | E43: 0.1 | F43: - | G43: - | H43: Amianto | I43: Pneumoconiose; Câncer no pulmão; Mesotelioma. | J43: Cassete condutivo com filtro de éster de celulose | K43: Método NIOSH 7402 | L43: Microscópia de Transmissão de Elétrons | M43: 2 | N43: 720 | P43: i
B44: Amônia | C44: Cód. e-Social: N. C. | D44: ppm | E44: 25 | F44: 35 | G44: 20 | H44: Amônia | I44: Dano olhos; Irritação TRS | J44: Filtro de éster de celulose | K44: Método NIOSH 6016 | L44: Cromatografia | M44: 0,1 - 0,5 | N44: 1,5 - 96 | O44: < 0,010 | P44: < 0,010 | Q44: 7726-95-6
B45: Antimônio | C45: Cód. e-Social: N. C. | D45: mg/m3 | E45: 0.5 | F45: - | G45: - | H45: Antimônio | I45: Irritações na pele; Irritações no TRS | J45: Filtro de éster de celulose | K45: Método NIOSH 7303 | L45: Espectrofotometria | M45: 1 - 4 | N45: 45 - 1000 | O45: < 0,005 | P45: < 0,005 | Q45: 106-97-8
B46: Arsênio | C46: Cód. e-Social: 01.01.001 | D46: mg/m3 | E46: 0.01 | F46: - | G46: - | H46: Arsênio | I46: Câncer do pulmão | J46: Filtro de éster de celulose | K46: Método NIOSH 7303 | L46: Espectrofotometria | M46: 1 - 4 | N46: 45 - 1000 | O46: < 0,005 | P46: < 0,005 | Q46: 71-36-3
B47: Bário | C47: Cód. e-Social: N. C. | D47: mg/m3 | E47: 0.5 | F47: - | G47: - | H47: Bário | I47: Irritação olhos, pele e GI; estim muscular | J47: Filtro de éster de celulose | K47: Método NIOSH 7303 | L47: Espectrofotometria | M47: 1 - 4 | N47: 45 - 1000 | O47: < 0,001 | P47: < 0,001 | Q47: 7440-43-9
B48: Benzeno | C48: Cód. e-Social: 01.03.001 | D48: ppm | E48: 0.02 | F48: - | G48: - | H48: Benzeno | I48: Síndrome mielodisplásica; Leucemia mieolóide aguda; Leucemia; Efeitos hematológicos; Dano cromossômico | J48: Tubo de Carvão Ativado | K48: Método NIOSH 1501 | L48: Cromatografia | M48: 0,02 - 0,2 | N48: 3 - 30 | O48: < 0,011 | P48: < 0,011 | Q48: 7439-92-1
B49: Berílio | C49: Cód. e-Social: 01.04.001 | D49: mg/m3 | E49: 5e-05 | F49: - | H49: Berílio | I49: Sensibilidade ao berílio; Doença crônica do berílio (beriliose) | J49: Filtro de éster de celulose | K49: Método NIOSH 7303 | L49: Espectrofotometria | M49: 2 para IOM | N49: 480 | O49: 1 | P49: 1 | Q49: NÃO ENCONTREI
B50: Borato de sódio | C50: Cód. e-Social: N. C. | D50: mg/m3 | E50: 2 | F50: 6 | G50: - | H50: Borato de sódio | I50: Irritação TRS | J50: Filtro de éster de celulose | K50: Método NIOSH 7303 | L50: Espectrofotometria | M50: 2 | N50: 480 | O50: 5 | P50: 5 | Q50: 74-90-8
B51: Boro | C51: Cód. e-Social: N. C. | D51: mg/m3 | E51: 1.76 | F51: 5.28 | G51: - | H51: Boro | I51: Irritação TRS | J51: Filtro de éster de celulose | K51: Método NIOSH 7303 | L51: Espectrofotometria | M51: 1 - 4 | N51: 240 - 960 | O51: 5 | P51: 5 | Q51: 110-82-7
B52: Bromo | C52: Cód. e-Social: 01.05.001 | D52: ppm | E52: 0.1 | F52: 0.2 | G52: 0.08 | H52: Bromo | I52: Irritação TRS e TRI; Dano pulmão | J52: Filtro de PTFE | K52: Método NIOSH 6001 | L52: Cromatografia | M52: 0.5 | N52: 7,5 - 30 | O52: < 0,002 | P52: < 0,002 | Q52: 108-93-0
B53: Butano (N-Butano) | C53: Cód. e-Social: 01.17.001 | D53: ppm | E53: - | F53: 1000 | G53: 470 | H53: Butano (N-Butano) | I53: Comprometimento do SNC | J53: Balão de Tedlar de 5 L | K53: Método T. 10-22/00 | L53: Cromatografia | M53: 0,02 - 0,2 | N53: máximo de 5 | O53: < 0,001 | P53: < 0,001 | Q53: 108-94-1
B54: Butanol | C54: Cód. e-Social: N. C. | D54: ppm | E54: - | F54: - | G54: 40 | H54: Butanol | I54: Irritação olhos e TRS | J54: Tubo de Carvão | K54: Método NIOSH 1401 | L54: Cromatografia | M54: 0,01 - 0,2 | N54: 2 - 10 | Q54: 110-83-8
B55: Butil Glicol | C55: Cód. e-Social: N. C. | D55: ppm | E55: 20 | F55: - | G55: 39 | H55: Butil Glicol | I55: Irritações nos olhos; Irritações no TRS | J55: Tubo de Carvão Ativado | K55: Método NIOSH 1403 | L55: Cromatografia | M55: 0,02 - 0,2 | N55: 1-10 | Q55: 111-76-2
B56: Cádmio | C56: Cód. e-Social: 01.06.001 | D56: mg/m3 | E56: 0.002 | F56: - | G56: - | H56: Cádmio | I56: Dano rins | J56: Filtro de éster de celulose | K56: Método NIOSH 7303 | L56: Espectrofotometria | M56: 1.7 | N56: 45 - 1000 | O56: < 0,001 | P56: < 0,001 | Q56: 287-92-3
B57: Chumbo | C57: Cód. e-Social: 01.08.001 | D57: mg/m3 | E57: 0.05 | F57: - | G57: 0.1 | H57: Chumbo | I57: Comprometimento do SNC; Comprometimento do sistema nervoso periférico; Efeitos hematológicos | J57: Filtro de éster de celulose | K57: Método NIOSH 7303 | L57: Espectrofotometria | M57: 1 - 4 | N57: 45 - 1000 | O57: < 0,001 | P57: < 0,001 | Q57: 7782-50-5
B58: Cianeto de Hidrogênio | C58: Cód. e-Social: N. C. | D58: ppm | E58: - | F58: 4.7 | G58: 8 | H58: Cianeto de Hidrogênio | I58: Irritações no TRS; Dor de cabeça; Náusea; Efeitos na tireóide | J58: Filtro de éster de celulose | K58: Método NIOSH 7904 | L58: Ions | M58: 0,5 - 1 | N58: 10 - 180 | O58: 0.0005 | Q58: 75-45-6
B59: Cianetos | C59: Cód. e-Social: N. C. | D59: ppm | E59: - | F59: 4.7 | G59: 8 | H59: Cianetos | I59: Irritações no trato respiratório superior; Dor de cabeça; Náusea; Efeitos na tireóide | J59: Filtro de éster de celulose | K59: Método NIOSH 7904 | L59: Ions | M59: 1 - 4 | N59: 180 | O59: 0.0005 | Q59: 67-66-3
B60: Ciclohexano | C60: Cód. e-Social: N. C. | D60: ppm | E60: 100 | F60: - | G60: 235 | H60: Ciclohexano | I60: Comprometimento do SNC; Irritações nos olhos; Irritações no TRS. | J60: Tubo de Carvão Ativado | K60: Método NIOSH 1500 | L60: Cromatografia | M60: 0,02 - 0,2 | N60: 2,5 - 5 | O60: < 0,007 | P60: < 0,007 | Q60: 7440-48-4
B61: Ciclohexanol | C61: Cód. e-Social: N. C. | D61: ppm | E61: 50 | F61: - | G61: 40 | H61: Ciclohexanol | I61: Irritação olhos; compr SNC | J61: Tubo de Carvão Ativado | K61: Método NIOSH 1402 | L61: Cromatografia | M61: 0,02 - 0,2 | N61: 1 - 10 | O61: < 0,003 | P61: < 0,003 | Q61: 7440-50-8
B62: Ciclohexanona | C62: Cód. e-Social: N. C. | D62: ppm | E62: 20 | F62: 50 | G62: - | H62: Ciclohexanona | I62: Irritação olhos e TRS | J62: Tubo de Carvão Ativado | K62: Método NIOSH 1300 | L62: Cromatografia | M62: 0,02 - 0,2 | N62: 1 - 10 | O62: < 0,002 | P62: < 0,002 | Q62: 7440-47-3
B63: Ciclohexeno | C63: Cód. e-Social: N. C. | D63: ppm | E63: 20 | F63: - | G63: - | H63: Ciclohexeno | I63: Efeito no fígado | J63: Tubo de Carvão Ativado | K63: Método NIOSH 1500 | L63: Cromatografia | M63: 0,02 - 0,2 | N63: 5 - 7 | O63: < 0,007 | P63: < 0,007 | Q63: 84989-04-8
B64: Ciclohexilamina | C64: Cód. e-Social: N. C. | D64: ppm | E64: 10 | F64: - | G64: 8 | H64: Ciclohexilamina | I64: Irritação olhos e TRS | J64: Tubo de Carvão Ativado | K64: Método OSHA PV 2016 | L64: Cromatografia | M64: 0,1 - 0,2 | N64: 10 - 20 | Q64: 98-82-8
B65: Ciclopentano | C65: Cód. e-Social: N. C. | D65: ppm | E65: 1000 | F65: - | G65: - | H65: Ciclopentano | I65: Comprometimento do SNC | J65: Tubo de Carvão Ativado | K65: Método NIOSH 1500 | L65: Cromatografia | M65: 0,02 - 0,2 | N65: 2,5 - 5 | O65: < 0,002 | P65: < 0,002 | Q65: 68334-30-5
B66: Cloro | C66: Cód. e-Social: 01.09.001 | D66: ppm | E66: 0.1 | F66: 0.4 | G66: 0.8 | H66: Cloro | I66: Irritação TRS; Extrema reação nas vias aéreas; Edema pulmonar. | J66: Impinger | K66: Método OSHA ID - 101 | L66: Cromatografia | M66: 1 - 2 | N66: 15 - 1000 | O66: < 0,002 | P66: < 0,002 | Q66: 123-42-2
B67: Clorodifluormetano | C67: Cód. e-Social: 01.09.001 | D67: ppm | E67: 1000 | F67: - | G67: 780 | H67: Clorodifluormetano | I67: Comprometimento do SNC; Asfixia; Senbilizante cardíaco | J67: Tubo de Carvão Ativado | K67: Método NIOSH 1018 | L67: Cromatografia | M67: 0,02 - 0,05 | N67: 1 - 4 | O67: < 0,007 | P67: < 0,007 | Q67: 76-14-2
B68: Clorofórmio | C68: Cód. e-Social: 01.09.001 | D68: ppm | E68: 10 | F68: - | G68: 20 | H68: Clorofórmio | I68: Dano fígado; dano embrio/fetal; compr SNC | J68: Tubo de Carvão Ativado | K68: Método NIOSH 1003 | L68: Cromatografia | M68: 0,02 - 0,2 | N68: 1 - 50 | O68: < 0,005 | P68: < 0,005 | Q68: 75-09-2
B69: Cobalto | C69: Cód. e-Social: N. C. | D69: mg/m3 | E69: 0.02 | F69: - | G69: - | H69: Cobalto | I69: Mudanças na função pulmonar. | J69: Filtro de éster de celulose | K69: Método NIOSH 7303 | L69: Espectrofotometria | M69: 2 | N69: 480 | O69: < 0,005 | P69: < 0,005 | Q69: 68-12-2
B70: Cobre | C70: Cód. e-Social: N. C. | D70: mg/m3 | E70: 1 | F70: - | G70: - | H70: Cobre | I70: Irritação; GI; febre dos fumos metálicos | J70: Filtro de éster de celulose | K70: Método NIOSH 7303 | L70: Espectrofotometria | M70: 1 - 4 | N70: 45 - 1000 | O70: < 0,005 | P70: < 0,005 | Q70: 124-38-9
B71: Cresol | C71: Cód. e-Social: N. C. | D71: mg/m3 | E71: 20 | F71: - | G71: - | H71: Cresol | I71: Irritações no TRS | J71: Filtro de fibra de vidro (IOM) + Tubo de resina XAD-7 de 100/50 | K71: Método NIOSH 2546 | L71: Cromatografia | M71: 0,01 - 0,1 | N71: 1 - 24 | Q71: 2025884
B72: Cromo | C72: Cód. e-Social: 01.10.001 | D72: mg/m3 | E72: 0.5 | F72: - | G72: - | H72: Cromo | I72: Irritações no TRS | J72: Filtro de éster de celulose | K72: Método NIOSH 7303 | L72: Espectrofotometria | M72: 2 para IOM | N72: 480 | O72: 1 | P72: < 0,02 | Q72: 10102-44-0
B73: Cromo Hexavalente | C73: Cód. e-Social: 01.10.001 | D73: mg/m3 | E73: 0.0002 | F73: 0.0005 | G73: - | H73: Cromo Hexavalente | I73: Câncer de Pulmão; Cancer sinonasal; Irritação Trato Respiratório; Asma. | J73: Filtro de fibra de vidro | K73: Método MDHS 14/3 | L73: Espectrofotometria | M73: 2 | N73: 480 - 960 | Q73: 13463-67-7
B74: Cumeno | C74: Cód. e-Social: 01.03.001 | D74: ppm | E74: 5 | F74: - | G74: 39 | H74: Cumeno | I74: Adenoma TRS; efeito neurológico | J74: Tubo de Carvão Ativado | K74: Método NIOSH 1501 | L74: Cromatografia | M74: 0,02 - 0,2 | N74: 1 - 30 | O74: < 0,007 | P74: < 0,007 | Q74: 7440-31-5
B75: Diacetona Álcool | C75: Cód. e-Social: N. C. | D75: ppm | E75: 50 | F75: - | G75: - | H75: Diacetona Álcool | I75: Irr olhos e TRS | K75: Método IT 10-07 | L75: Cromatografia | M75: 0,02 - 0,2 | N75: 1 - 10 | P75: < 0,004 | Q75: 100-42-5
B76: Diclorometano | C76: Cód. e-Social: 01.09.001 | D76: ppm | E76: 50 | F76: - | G76: 156 | H76: Diclorometano | I76: Carboxihemoglobinemia; Comprometimento do SNC. | J76: Tubo de Carvão Ativado | K76: Método NIOSH 1005 | L76: Cromatografia | M76: 0,02 - 0,2 | N76: 0,5 - 2,5 | Q76: 64-17-5
B77: Diclorotetrafluoretano | C77: Cód. e-Social: 01.09.001 | D77: ppm | E77: 1000 | F77: - | G77: 780 | H77: Diclorotetrafluoretano | I77: Efeito na função pulmonar | J77: Tubo de Carvão Ativado | K77: Método NIOSH 1018 | L77: Cromatografia | M77: 0,02 - 0,05 | N77: 1 - 4 | O77: < 0,007 | P77: < 0,007 | Q77: 141-43-5
B78: Diesel | C78: Cód. e-Social: 01.17.001 | D78: mg/m3 | E78: 100 | F78: - | G78: - | H78: Diesel | I78: Dermatite | J78: Filtro de Fibra de Vidro + Tubo de Carvão Ativado | K78: Método NIOSH 1550 | L78: Cromatografia | M78: 2 | N78: 480 | O78: - | P78: - | Q78: 13588-28-8
B79: Dimetilformamida | C79: Cód. e-Social: N. C. | D79: ppm | E79: 5 | F79: - | G79: 8 | H79: Dimetilformamida | I79: Danos no fígado; Irritação nos olhos e TRS | J79: Tubo de Sílica gel | K79: Método NIOSH 2004 | L79: Cromatografia | M79: 0,02 - 1 | N79: 15 - 80 | O79: < 0,009 | P79: < 0,009
B80: Dióxido de carbono | C80: Cód. e-Social: N. C. | D80: ppm | E80: 5000 | F80: 30000 | G80: 3900 | H80: Dióxido de carbono | I80: Asfixia | J80: Balão de tedlar de 5 L | K80: Método NIOSH 6603 | L80: Cromatografia | M80: 0,02 - 0,1 | N80: 5 | O80: < 0,050 | P80: < 0,050 | Q80: 112-34-5
B81: Dióxido de enxofre | C81: Cód. e-Social: N. C. | D81: ppm | E81: - | F81: 0.25 | G81: 4 | H81: Dióxido de enxofre | I81: Efeitos na função pulmonar; Irritação TRI | J81: Filtro de éster de celulose | K81: Método NIOSH 6004 | L81: Cromatografia | M81: 0,5 - 1,5 | N81: 4 - 200 | O81: < 0,002 | P81: < 0,002 | Q81: 100-41-4
B82: Dióxido de nitrogênio | C82: Cód. e-Social: N. C. | D82: ppm | E82: 0.2 | F82: - | G82: 4 | H82: Dióxido de nitrogênio | I82: Irritação TRI | J82: Tubo de Carvão Ativado | K82: Método NIOSH 6014 | L82: Espectrofotometria | M82: 0.025 | N82: 3 - 6 | O82: < 0,001 | P82: < 0,001 | Q82: 74-85-1
B83: Dióxido de Titânio | C83: Cód. e-Social: N. C. | D83: mg/m3 | E83: 2.5 | F83: - | G83: - | H83: Dióxido de Titânio | I83: Irritação no TRI, Pneumoconiose | J83: Filtro de éster de celulose | K83: Método NIOSH 7303 | L83: Espectrofotometria | M83: 1 - 4 | N83: 45 - 1000 | O83: < 0,017 | P83: < 0,017 | Q83: 107-21-1
B84: Estanho | C84: Cód. e-Social: N. C. | D84: mg/m3 | E84: 2 | F84: - | G84: - | H84: Estanho | I84: Pneumoconiose | J84: Filtro de éster de celulose | K84: Método NIOSH 7303 | L84: Espectrofotometria | M84: 2 | N84: 480 | O84: < 0,001 | P84: < 0,001 | Q84: 108-95-2
B85: Estanho - Compostos Orgânicos | C85: Cód. e-Social: N. C. | D85: mg/m3 | E85: 0.1 | F85: 0.2 | G85: - | H85: Estanho - Compostos Orgânicos | I85: Irritações nos olhos; Irritações no TRS; Dor de cabeça; Náusea; Efeitos no SNC; Efeitos no SI | J85: Filtro de éster de celulose | K85: Método NIOSH 7303 | L85: Espectrofotometria | M85: 2 | N85: 480 | Q85: 1309-37-1
B86: Estireno | C86: Cód. e-Social: 01.03.002 | D86: ppm | E86: 10 | F86: 20 | G86: 78 | H86: Estireno | I86: Comprometimento do SNC; Comprometimento do sistema auditivo; Irritações no TRS; Neuropatia periférica; Desordens visuais | J86: Tubo de Carvão Ativado | K86: Método NIOSH 1501 | L86: Cromatografia | M86: 0,02 - 1 | N86: 1 - 14 | O86: < 0,004 | P86: < 0,004 | Q86: 16984-48-8
B87: Etanol | C87: Cód. e-Social: N. C. | D87: ppm | E87: - | F87: 1000 | G87: 780 | H87: Etanol | I87: Irritação TRS | J87: Tubo de Carvão Ativado | K87: Método NIOSH 1400 | L87: Cromatografia | M87: 0,02 - 0,05 | N87: 0,1 - 1 | O87: < 0,007 | P87: < 0,007 | Q87: 50-00-0
B88: Etanolamina | C88: Cód. e-Social: N. C. | D88: ppm | E88: 3 | F88: 6 | G88: - | H88: Etanolamina | I88: Irritação nos olhos e pele. | J88: Tubo de resina XAD-2 de 80/40 mg | K88: Método OSHA PV2111 - HPLC | L88: Cromatografia | M88: 0,01 - 0,1 | N88: 1-20 | Q88: 7723-14-0
B89: Etér metílico de dipropileno Glicol | C89: Cód. e-Social: N. C. | D89: ppm | E89: 50 | F89: - | G89: - | H89: Etér metílico de dipropileno Glicol | I89: Danos no fígado; Efeitos no SNC | J89: Tubo de Chromosorb | K89: Método PA 7.2-123 | L89: Cromatografia | M89: 0,01 - 0,05 | N89: 0,1 - 1 | O89: < 0,007 | P89: < 0,007 | Q89: 8002-74-2
B90: Etér metílico do monopropileno Glicol | C90: Cód. e-Social: N. C. | D90: ppm | E90: 44 | F90: 88 | G90: - | H90: Etér metílico do monopropileno Glicol | I90: Irritação nos olhos; Irritação no TRS | J90: Tubo de Carvão Ativado | K90: Método OSHA 99 | L90: Cromatografia | M90: 0,01 - 0,05 | N90: 0,1 - 1 | O90: < 0,007 | P90: < 0,007 | Q90: 86290-81-5
B91: Éter monobutílico de dietileno glicol | C91: Cód. e-Social: N. C. | D91: ppm | E91: 10 | F91: - | G91: - | H91: Éter monobutílico de dietileno glicol | I91: Danos no fígado; Danos nos rins; Efeitos hematológicos | J91: Tubo de Carvão Ativado | K91: Método OSHA PV 2095 | L91: Cromatografia | M91: 2 | N91: 480 | Q91: 64742-49-0
B92: Etilbenzeno | C92: Cód. e-Social: 01.19.035 | D92: ppm | E92: 20 | F92: - | G92: 78 | H92: Etilbenzeno | I92: Irritações no TRS; Irritações nos olhos; Danos nos rins (nefrotoxicidade); Comprometimento do SNC; Ototoxicidade | J92: Tubo de Carvão Ativado | K92: Método NIOSH 1501 | L92: Cromatografia | M92: 0,02 - 0,2 | N92: 1 - 24 | O92: < 0,001 | P92: < 0,001 | Q92: 123-31-9
B93: Etileno | C93: Cód. e-Social: N. C. | D93: ppm | E93: 200 | F93: - | G93: - | H93: Etileno | I93: Asfixia | J93: Tubo de Anasorb 747 | K93: Método NIOSH 1614 | L93: Cromatografia | M93: 0,05 - 0,15 | N93: 1 - 24 | O93: - | P93: - | Q93: 1310-58-3
B94: Etileno Glicol | C94: Cód. e-Social: N. C. | D94: ppm | E94: 25 | F94: 50 | G94: - | H94: Etileno Glicol | I94: Irritações no trato respiratório superior | J94: Tubo de Carvão Ativado | K94: Método NIOSH 5523 | L94: Cromatografia | M94: 0,5 - 2 | N94: 5 - 60 | Q94: 1310-73-2
B95: Fenol | C95: Cód. e-Social: 01.03.001 | D95: ppm | E95: 5 | F95: - | G95: 4 | H95: Fenol | I95: Irritação TRS; dano pulmonar; compr SNC | J95: Tubo de resina XAD-7 | K95: Método NIOSH 2546 | L95: Cromatografia | M95: 0,02 - 0,1 | N95: 1 - 24 | O95: < 0,010 | P95: < 0,010 | Q95: 1305-62-0
B96: Ferro | C96: Cód. e-Social: N. C. | D96: mg/m3 | E96: 5 | F96: - | G96: - | H96: Ferro | I96: Pneumoconiose | J96: Filtro de éster de celulose | K96: Método NIOSH 7303 | L96: Espectrofotometria | M96: 1 - 4 | N96: 240 - 960 | O96: < 0,005 | P96: < 0,005 | Q96: 128-37-0
B97: Fluoretos | C97: Cód. e-Social: N. C. | D97: mg/m3 | E97: 2.5 | F97: - | G97: - | H97: Fluoretos | I97: Danos ossos; fluorose | J97: Filtro de éster de celulose | K97: Método NIOSH 7902 | L97: Cromatografia | M97: 1 - 2 | N97: 12 a 800 | O97: < 0,002 | P97: < 0,002 | Q97: 7553-56-2
B98: Formaldeído | C98: Cód. e-Social: N. C. | D98: ppm | E98: 0.1 | F98: 0.3 | G98: 1.6 | H98: Formaldeído | I98: Irritação olhos e TRS; Cancêr TRS. | J98: Tubo de Sílica gel | K98: Método NIOSH 2016 | L98: Cromatografia | M98: 0,03 - 1,5 | N98: 1 a 15 | O98: < 0,001 | P98: < 0,001 | Q98: 78-59-1
B99: Fosfina | C99: Cód. e-Social: 01.12.001 | D99: ppm | E99: 0.05 | F99: 0.15 | G99: 0.23 | H99: Fosfina | I99: Irritação trato respiratório; edema pulmonar | J99: Filtro de Fibra de Vidro | K99: Método NIOSH 7303 | L99: Espectrofotometria | M99: 1 | N99: 240 | Q99: 67-63-0
B100: Fósforo | C100: Cód. e-Social: 01.12.001 | D100: mg/m3 | E100: 0.1 | F100: - | G100: - | H100: Fósforo | I100: Irritação TRI, TRS e GI; dano fígado | J100: Tubo de tenax | K100: Método NIOSH 7905 | L100: Cromatografia | M100: 1 - 4 | N100: 45 - 1000 | O100: < 0,001 | P100: < 0,001 | Q100: 78-83-1
...

Sheet Lista de Empresa
A1: Identificação | B1: CNPJ | C1: Endereçoo
A2: Labsoft | B2: 05.412.271/0001-78 | C2: Rua Vigário João José Rodrigues, 905 - 7º Andar Centro Jundiaí/São Paulo
A3: 11342 Sociedade Fogas Ltda - Manaus | B3: 4563672000166 | C3: Rua Rio Quixito, 86 - Vila Buriti Manaus/Amazonas
A4: Sociedade Fogas Ltda - Santarém | B4: 04563672000590 | C4: Avenida Cuiba, Lote 5 - Area Portuária da CIA, doca do Pará Sale Santarém/Pará
A5: Placibras da Amazônia Ltda | B5: 5338882000202 | C5: Avenida Autaz Mirim, 2645 - Armando Mendes Manaus/Amazonas
A6: Componel Industria e Comércio Ltda | B6: 57593253000567 | C6: Avenida Açaí, 1325 - Distrito Industrial Manaus/Amazonas
A7: Pam Industria de Plasticos Injetados Ltda - Filial (04.413.977/0007-87) | B7: 4413977000787 | C7: Avenida Solimões, 105 - Lote 2.31 Distrito Industrial I Manaus/Amazonas
A8: Stratura Asfaltos S.A | B8: 59128553001220 | C8: Av. Rodrigo Otávio, 2.890 - Sala 03 Centro Comercial Distrito Industrial I Manaus/Amazonas
A9: Naturex - Ingredientes Naturais Ltda | B9: 3899381000180 | C9: Av. Buriti, 5.391 - Distrito Industrial Manaus/Amazonas
A10: 11349 Hisamitsu Farmaceutica do Brasil Ltda | B10: 49383250000147 | C10: Av. Buriti, 1.050 - Distrito Industrial Manaus/Amazonas
A11: Andrade Gutierrez Engenharia S/A | B11: 17262213025936 | C11: Av. Djalma Batista, 3.637 - Sala 08 Flores Manaus/Amazonas
A12: Tigre Materiais e Soluções Para Construção Ltda. | B12: 8862530000584 | C12: Av. Buriti, 3.501 - Lote 03 Distrito Industrial I Manaus/Amazonas
... A25: 11364 Flex Impor. Expor. Ind. E Comércio de Máquina e Motores Ltda | B25: 22798094000129 | C25: Av. Buriti, 4.821 - Distrito Industrial Manaus/Amazonas
A26: 11365 Flex Impor. Expor. Ind. E Comércio de Máquina e Motores Ltda (Galpão 01) | C26: Rua da Granja Azul, 03 - Galpão 01 Colônia Oliveira Machado Manaus/Amazonas
A27: Amazon Industria de Gelo e Bebidas Ltda | B27: 02402867000522 | C27: Rua da Granja Azul, n° 03 - Galpão 01 Col. Oliveira Machado Manaus/Amazonas
A28: J Cruz Indústria de Bebidas Ltda (Amazon Refrigerante - Filial) | B28: 4398251000550 | C28: Rua José Romão, 452 - São José Operário Manaus/Amazonas
A29: 11368 D.D Williamson do Brasil Ltda | B29: 02789565000125 | C29: Av. Buriti, 5.680 - Distrito Industral Manaus/Amazonas
A30: 11369 Eternal Ind. Com. Serv. e Trat de Resíduos da Amazônia Ltda | B30: 84527274000123 | C30: Rua Guiana Francesa, 01 - Distrito Industial II Manaus/Amazonas
A31: GRI Koleta - Gerenciamento de Resíduos Industriais S.A | B31: 4517241001135 | C31: Rua Constelação de Gêmeos, 169 - Galpão 02 Aleixo Manaus/Amazonas
A32: F E Isaías de Lima (Ceramica LIMA) | B32: 22815369000195 | C32: Rural S/N - Km 40 - Rural S/N - Km 40 - Área Rural de Manacapuru Manacapuru Manaus/Amazonas
A33: Sodecia Automotive Manaus Ltda | B33: 2499629000153 | C33: Rua Gisele, 1.000 - Mauazinho Manaus/Amazonas
A34: Amcor Embalagens da Amazônia Ltda | B34: 84127208000166 | C34: Rua Anhandui, 306 - Edifício D Flores Manaus/Amazonas
A35: Musashi da Amazônia Ltda | B35: 4944068000180 | C35: Av. Flamboyant, 931 - Distrito Industrial II Manaus/Amazonas
A36: 11375 Caloi Norte S.A | B36: 4301024000131 | C36: Av. Abiurana, 150 A - Distrito Industrial Manaus/Amazonas
A37: 11376 Agropecuária Jayoro Ltda | B37: 5827977000109 | C37: Est. BR 174 S/N - Zona Rural Ramal 14 Km 120 Presidente Figueiredo/Amazonas
A38: Norte Ambiental Tratamento de Resíduos Ltda | B38: 14214776000119 | C38: Est. Manoel Urbano S/N - Km 02 Iranduba/Amazonas
... A411: VP FLEXGEN BRAZIL SPE LTDA - HUMAITA | B411: 28231767000574 | C411: Rua 01 S/N° - Parque Industrial Humaitá/Amazonas
A412: TST José Emiliano da Silva | B412: 00063597330215
A413: BDA Serviços em construção e Comercio EIRELI | B413: 17010074000101 | C413: Av. Jutai, n° 124 - Nossa Senhora das Graças Manaus/Amazonas
A414: Procter e Gamble do Brasil S.A - Rio Solimões | B414: 59476770000158 | C414: Av. Guaruba, Nº 740 Distrito Industrial Manaus/Amazonas
A415: Francilene Mendonça da Silva (Marajoara) | B415: 31785469000107 | C415: Rua Marrocos, nº 190 - Flores Manaus/Amazonas
A416: Jr Comércio de Artefatos Metálicos Ltda | B416: 09565801000179 | C416: São Tomaz de Aquino, nº 158 - São Geraldo Manaus/Amazonas
A417: Auto Post Ozival XI ( Grupo Oziel Mustafa) | B417: 04643904001168 | C417: Avenida Torquato Tapajós, n.º 5201 A - Flores Manaus/Amazonas
A418: Glayciane Sabino Laranjeira | B418: 68872410215 | C418: - Manaus/Amazonas
A419: Emam Logistica LTDA | B419: 11105987000125 | C419: R.Nelson Rodrigues 01 - Compensa Manaus/Amazonas
A420: 11768 Intelbras S.A Ind. De Telecomunicação Eletrônica Brasileira | B420: 82901000001522 | C420: Av. Tefé, n° 3105 - Japiim Manaus/Amazonas
A421: Hitachi Astemo Manaus Chassis Systens LTDA (Showa) | C421: Rua Quixito, n° 1376 - Distrito Industrial Manaus/Amazonas
A422: Engenheira Carolina
A423: Amazon Aço Indústria e Comércio LTDA | B423: 05477207000175 | C423: Av. Puraquequara, N. 5328 - Puraquequara Manaus/Amazonas
A424: Navegação Cunha LTDA - MAO | B424: 04616801000137 | C424: Rua da Granja Azul N. 02 - Terreo Colônia Oliveira Machado Manaus/Amazonas
A425: 11774 Zilia Technologies Industria e Comércio de Componentes Eletrônicos LTDA | B425: 11576445000211 | C425: Av. Dos Oitis, n° 1720 - Distrito Industrial II Manaus/Amazonas
A426: VP Flexgen (Brazil) SPE Ltda - São Gabriel da Cachoeira | B426: 28231767000493 | C426: Estrada de Camanaus, n° S/N - Zona Rural Manaus/Amazonas
A427: SMX Agroindustrial Ltda | B427: 05399225000186 | C427: Estrada ZF 1 - KM 26/ Distritro Agropecuário da Suframa Manaus/Amazonas
A428: Francisco Afonso de Souza – EPP | B428: 04763698000158 | C428: Rua Santa Ana Nery, N° 07, Quadra D, Lote 07 Carijó - Coroado Manaus/Amazonas
A429: La Rondine Indústria e Comércio de Embalagens Ltda | B429: 04176315000145 | C429: AV. SOLIMÕES, 805 - DISTRITO INDUSTRIAL I Manaus/Amazonas
A430: Sociedade Porvir Cientifico (La Salle) | B430: 92741990004124 | C430: Av. Dom Pedro I, N° 151 - Dom Pedro Manaus/Amazonas
A431: Amazon Etiquetas Indústria e Comércio Ltda | B431: 03486616000148 | C431: Rua Germanio, N° 443 - Vila da Prata Manaus/Amazonas
A432: Engenheiro Marivaldo
A433: GD Santos
A434: Tuboaços da Amazônia LTDA | B434: 05236056000163 | C434: Av Tefe, n° 2.837 - Japiim Manaus/Amazonas
A435: Apis Floresta Produtos Apicolos LTDA | B435: 84664937000151 | C435: Rua Juruaia, n° 141 - Santa Etelvina Manaus/Amazonas
A436: Tim Live Manaus | B436: 02421421003137 | C436: Rua Guilherme Paraense, 93, Adrianópolis - Adrianopólis Manaus/Amazonas
A437: Dipon Gás | B437: 01506543000148 | C437: R. Deolindo Tavares, n° 133 - Imbiribeira Recife/Pernambuco
A438: JDS Serviços de Estrutura Metálica Ltda | B438: 09502722000119 | C438: Flor de Laranjeira, N° 204 - Tarumã Manaus/Amazonas
A439: CNN – Cia Norte de Navegação | B439: 14160269000140 | C439: Rua Desembargador Cesar do Rego, N° 850 - Colônia Antônio Aleixo Manaus/Amazonas
A440: Speed Transporte Multimodal de Cargas Limitada | B440: 31145051000135 | C440: Av. Solimões N. 500 - Distrito Industrial II Manaus/Amazonas
A441: Serviço Nacional de Aprendizagem - SENAI | B441: 03795071001350 | C441: Av. Orlando Gomes, N° 1845, Piata - Salvador Salvador/Bahia
A442: 11791 Terminal Portuário Novo Remanso S/A | B442: 13999991000100 | C442: Ramal Macaco Cego, 755 - Bloco TGSA Rural Itacoatiara/Amazonas
A443: Masa Indústria de Plásticos da Amazônia Ltda | B443: 31303127000103 | C443: AV. SOLIMÕES, 805 - Distrito Industrial Manaus/Amazonas
A444: Allan Kardec Bandeira de Melo Filho | C444: Alameda Rio Negro, Numero 02. Condominio Vila da barra, casa 45 - Manaus/Amazonas
A445: Alterosa Empreendimentos Imobiliários Ltda | B445: 28014788000376 | C445: Rua Acre, N° 428 - Nossa Senhora das Graças Manaus/Amazonas
A446: Nascseg Assessoria e Consultoria Empresarial | B446: 11993348000143 | C446: Travessa L - 6 (CJ COHAB), n° 213 Compina de Icoaraci Belém/Pará
A447: Frigorífico Rio Maria Ltda | B447: 04749233000142 | C447: Rod. BR 155, KM 85,3 - Belém/Pará
A448: Marthina S da Costa Serviços | B448: 29616375000162 | C448: Av. 01, N° 03 - Iranduba/Amazonas
A449: BP Serviços de Esterilização SPE S.A´- Matriz | B449: 21821773000109 | C449: Travessa Castro Leite, - Lote 3 - Parque Shangrila VII Parque Dez de Novembro Manaus/Amazonas
A450: Biopulos Com. e Rep. de Medicamentos e Serviços de Equipamentos Medico-Hospitalares Ltda | B450: 08992424000191 | C450: Av. Cosme Ferreira, N° 1877 - Aleixo Manaus/Amazonas
A451: Civilcorp Icorporações LTDA - Residencial Morada dos Passaros | B451: 03187301000164 | C451: Av. André Araújo, N° 2.755 - Aleixo Manaus/Amazonas
A452: 11801 Positivo Tecnologia S.A | B452: 81243735001977 | C452: Rua Javari N° 1155 - Distrito Industrial Manaus/Amazonas
A453: Foco Agencia de Cargas LTDA | B453: 07784967000401 | C453: Av. Torquato Tapajós, n° 1960 - Flores Manaus/Amazonas
A454: Petrobras Distribuidora S.A - BARAC | B454: 34274233014588 | C454: Av. Dr. Zany, n° 852 - Livramento Caracaraí/Roraima
A455: Marcos José Miiler | B455: 00001655364111
A456: 11805 FIT Instituto de Tecnologia da Amazonia | B456: 28494214000180 | C456: Av. Torquato Tapajós, n° 7200A - Colônia Terra Nova Manaus/Amazonas
A457: Serv. Autonomo de Água e Esgoto de Itacoatiara | B457: 04320180000140 | C457: Rua Adamastor de Figueiredo, n° 2401 - Centro Manaus/Amazonas
A458: Dafra da Amazonia Ind. De Com de Motocicletas LTDA | B458: 08322908000123 | C458: Av. Torquato Tapajós, n° 11.600 - Santa Etelvina Manaus/Amazonas
A459: Elcoa Industria e Comércio LTDA | B459: 02782499000242 | C459: Rua Javari, n° 1.065 - Distrito Industrial Manaus/Amazonas
A460: Ocupacional Safety Serviços Medicos Amb. | B460: 22568408000105 | C460: Rua Gonçalves Dias n° 145 Centro Porto Velho/Rondônia
A461: Residencial Villa Poupex | B461: 11040225000198 | C461: Rua Sobral nº 181 - São José Operário Manaus/Amazonas
A462: 11811 Valgroup AM Indústria de Embalagens Flexiveis LTDA | B462: 04807608000183 | C462: Rua Tento, n° 763 - Distrito Industrial II Manaus/Amazonas
A463: Vista Serrana Empreendimentos Imobiliarios LTDA | B463: 31259382000287 | C463: Av. Torquato Tapajós, n° 0 Lote 2 - Lote 02 Col. Terra Nova Manaus/Amazonas
A464: Município de Pindaré | B464: 06189344000177 | C464: Av. Elias Haikel, S/N - Centro Manaus/Amazonas
A465: Chibatão Navegação e Comércio LTDA - Alfandegado | B465: 84098383000172 | C465: Rua Zebu, n° 201 - Colônia Oliveira Machado Manaus/Amazonas
A466: Mais Proteção Santarem | C466: - Santarém/Pará
A467: Felipe Ricardo Oliveira Alencar - Everest Consultoria | B467: 35599255000105 | C467: Rua Canoa Quebrada, n° 80 - Tarumã Manaus/Amazonas
A468: Roberto Wag Chen
A469: Françoise Paloma Mamede | B469: 00051535556234
A470: Pinheiro e Rodrigues LTDA - Frigorifico de Pescado da Am | B470: 84488170000157 | C470: Av. Correnteza n° 2472 - Corrente Manacapuru Manacapuru/Amazonas
A471: 11820 Itacol Com e Serv. De Material de Construção LTDA | B471: 01426994000175 | C471: Rua Rio Mutuzinho, n° 839 - Armando Mendes Manaus/Amazonas
A472: CONTROL AMB. SUSTENTABILIDADE E MEIO AMBIENTE S.A | B472: 10550896000721 | C472: Rua Rio Javari, n° 16 - Nossa senhora das Graças Manaus/Amazonas
A473: Alcance Transportes LTDA | B473: 02149109000544 | C473: Rua Marques de Muritiba, n° 528 - Flores Manaus/Amazonas
A474: Nort Tech Serviços em Energia LTDA | B474: 33822061000436 | C474: Av. Torquato Tapajós, n° 12363 - Novo Israel Manaus/Amazonas
A475: José Ribamar
A476: Kawasaki Motores Do Brasil Ltda | C476: Rua Arraias, n° 286 - Colônia Antônio Aleixo Manaus/Amazonas
A477: Jucirley Rodrigues | B477: 00056002696253 | C477: Estrada Manoel Urbano Km 50 - Iranduba/Amazonas
A478: Tercom Terraplanagem LTDA | B478: 14198006000120 | C478: Av. Max Teixeira, n° 3.159 - Cidade Nova Manaus/Amazonas
A479: Real Bebidas da Amazonia LTDA | B479: 06990011000142 | C479: Rua Maceio, n° 426 - Adrianópolis Manaus/Amazonas
A480: Jesus Eduardo Barbosa Martins | B480: 20191621000107 | C480: R. Gabriel Gomes Silva , n° 23 - Col. Santo Antonio Manaus/Amazonas
A481: Chibatão Navegação e Comércio LTDA - ATR | B481: 84098383000687 | C481: Av. Presidente Kennedy, n° 1520 - Colônia Oliveira Machado Manaus/Amazonas
A482: Chibatão Navegação e Comércio LTDA - Colonia | B482: 84098383000415 | C482: Av. Presidente Kennedy, n° 1850 - Colônia Oliveira Machado Manaus/Amazonas
A483: J. F. De Oliveira Navegação LTDA - Ceasa | B483: 22797070000155 | C483: Av. Presidente Kennedy, n° 1850 - Colônia Oliveira Machado Manaus/Amazonas
A484: 11833 FW Serviços e Manutenção Elétrica LTDA | B484: 18568875000150 | C484: Rua Tupiniquim, n° 32 - Cidade Nova Manaus/Amazonas
...

Sheet TLV _Andrea
A1: Agente Químico | B1: e-Social | D1: Unidade | F1: TWA | G1: STEL | H1: NR 15 | J1: Bases de Efeitos Críticos | K1: Amostrador | L1: CAS | M1: Método de Análise | N1: Metodologia de Amostragem | O1: Vazão | P1: Volume
A2: Acetaldeído | B2: N. C. | C2: Acetaldeído | D2: ppm | E2: Acetaldeído | F2: - | G2: 22 | H2: 78 | I2: Acetaldeído | J2: Irritação no TRS e olhos. | K2: TSG | M2: EPA 8315 | N2: Cromatografia | O2: 0,5 - 1,5 | P2: 30 - 500
A3: Acetamida | B3: N. C. | C3: Acetamida | D3: ppm | E3: Acetamida | F3: 0.88 | G3: - | H3: - | I3: Acetamida | J3: Irritação no TRS e olhos. | K3: -
A4: Acetato de benzila | B4: N. C. | C4: Acetato de benzila | D4: ppm | E4: Acetato de benzila | F4: 8,8 | G4: - | H4: - | I4: Acetato de benzila | J4: Irritação no TRS. | K4: -
A5: Acetato de n-butila | B5: N. C. | C5: Acetato de n-butila | D5: ppm | E5: Acetato de n-butila | F5: 44 | G5: 132 | H5: - | I5: Acetato de n-butila | J5: Irritação nos olhos e no TRS. | K5: TC | M5: NIOSH 1450 | N5: Cromatografia | O5: 0,01 - 0,2 | P5: 1 - 10
A6: Acetato de sec-butila | B6: N. C. | C6: Acetato de sec-butila | D6: ppm | E6: Acetato de sec-butila | F6: 176 | G6: - | H6: - | I6: Acetato de sec-butila | J6: Irritação nos olhos e no TRS. | K6: TC | M6: NIOSH 1450 | N6: Cromatografia | O6: 0,01 - 0,2 | P6: 1 - 10
A7: Acetato de terc-butila | B7: N. C. | C7: Acetato de terc-butila | D7: ppm | E7: Acetato de terc-butila | F7: 176 | G7: - | H7: - | I7: Acetato de terc-butila | J7: Irritação nos olhos e no TRS. | K7: TC | M7: NIOSH 1450 | N7: Cromatografia | O7: 0,01 - 0,2 | P7: 1 - 10
A8: Acetato de 2-butoxietila | B8: N. C. | C8: Acetato de 2-butoxietila | D8: ppm | E8: Acetato de 2-butoxietila | F8: 17,6 | G8: - | H8: - | I8: Acetato de 2-butoxietila | J8: Hemólise | K8: -
A9: Acetato de etila | B9: N. C. | C9: Acetato de etila | D9: ppm | E9: Acetato de etila | F9: 352 | G9: - | H9: 310 | I9: Acetato de etila | J9: Irritação nos olhos e no TRS. | K9: TC | M9: NIOSH 1457 | N9: Cromatografia | O9: 0,01 - 0,2 | P9: <10
A10: Acetato de 2-etoxietila | B10: N. C. | C10: Acetato de 2-etoxietila | D10: ppm | E10: Acetato de 2-etoxietila | F10: 4.4 | G10: - | I10: Acetato de 2-etoxietila | J10: Dano reprodutivo masculino. | K10: TC | M10: NIOSH 1450 | N10: Cromatografia | O10: 0,01 - 0,2 | P10: 1 - 10
A11: Acetato de sec-hexila | B11: N. C. | C11: Acetato de sec-hexila | D11: ppm | E11: Acetato de sec-hexila | F11: 17.6 | G11: - | H11: - | I11: Acetato de sec-hexila | J11: Irritação nos olhos e no TRS. | K11: -
A12: Acetato de isobutila | B12: N. C. | C12: Acetato de isobutila | D12: ppm | E12: Acetato de isobutila | F12: 132 | G12: - | H12: - | I12: Acetato de isobutila | J12: Irritação nos olhos e no TRS. | K12: TC | M12: NIOSH 1450 | N12: Cromatografia | O12: 0,01 - 0,2 | P12: 1 - 10
A13: Acetato de isopropila | B13: N. C. | C13: Acetato de isopropila | D13: ppm | E13: Acetato de isopropila | F13: 88 | G13: 132 | H13: - | I13: Acetato de isopropila | J13: Irritação nos olhos e no TRS; Comprometimento SNC. | K13: TC | M13: NIOSH 1454 | N13: Cromatografia | O13: 0,01 - 0,2 | P13: 0,1 - 9
A14: Acetato de metila | B14: N. C. | C14: Acetato de metila | D14: ppm | E14: Acetato de metila | F14: 176 | G14: 220 | H14: - | I14: Acetato de metila | J14: Dor de cabeça; tontura; náusea; dano olhos (degeneração das células ganglionares da retina). | K14: TC | M14: NIOSH 1458 | N14: Cromatografia | O14: 0,1 - 0,2 | P14: 0,2 - 10
A15: Acetato de 2-metoxietila | B15: N. C. | C15: Acetato de 2-metoxietila | D15: ppm | E15: Acetato de 2-metoxietila | F15: 0.088 | G15: - | H15: - | I15: Acetato de 2-metoxietila | J15: Efeito hematológico; Efeito reprodutivo. | K15: - | M15: - | N15: - | O15: - | P15: -
A16: Acetato de n-propila | B16: N. C. | C16: Acetato de n-propila | D16: ppm | E16: Acetato de n-propila | F16: 176 | G16: 220 | H16: - | I16: Acetato de n-propila | J16: Irritação nos olhos e no TRS. | K16: TC | M16: NIOSH 1450 | N16: Cromatografia | O16: 0,01 - 0,2 | P16: 1 - 10
A17: Acetato de pentila | B17: N. C. | C17: Acetato de pentila | D17: ppm | E17: Acetato de pentila | F17: 44 | G17: 88 | H17: - | I17: Acetato de pentila | J17: Irritação no TRS. | K17: - | M17: - | N17: - | O17: - | P17: -
A18: Acetato de vinila | B18: N. C. | C18: Acetato de vinila | D18: ppm | E18: Acetato de vinila | F18: 8,8 | G18: 13,2 | H18: - | I18: Acetato de vinila | J18: Irritação nos olhos, pele e TRS; Comprometimento do SNC. | K18: TC | M18: NIOSH 1453 | N18: Cromatografia | O18: 0,01 - 0,2 | P18: 1 - 24
A19: Acetileno | B19: N. C. | C19: Acetileno | D19: - | E19: Acetileno | F19: - | G19: - | H19: - | I19: Acetileno | J19: Asfixia | K19: - | M19: - | N19: - | O19: - | P19: -
A20: Acetofenona | B20: N. C. | C20: Acetofenona | D20: ppm | E20: Acetofenona | F20: 8,8 | G20: - | H20: - | I20: Acetofenona | J20: Irritação no TRS, comprometimento do SNC, aborto. | K20: Tenax GC | M20: OSHA PV 2003 | N20: Cromatografia | O20: 0,01 - 0,2 | P20: 1 - 24
A21: Acetona | B21: N. C. | C21: Acetona | D21: ppm | E21: Acetona | F21: 220 | G21: 440 | H21: 780 | I21: Acetona | J21: Irritação no TRS, comprometimento do SNC, efeito hematológico). | K21: TC | M21: NIOSH 1300 | N21: Cromatografia | O21: 0,01 - 0,2 | P21: 0,5 - 3
A22: Acetato cianidrina | B22: N. C. | C22: Acetato cianidrina | D22: mg/m3 | E22: Acetato cianidrina | F22: - | G22: 4,4 | H22: - | I22: Acetato cianidrina | J22: Irritação no TRS; dor de cabeça; hipoxia/cianose. | K22: -
A23: Acetonitrila | B23: N. C. | C23: Acetonitrila | D23: ppm | E23: Acetonitrila | F23: 17,6 | G23: - | H23: 30 | I23: Acetonitrila | J23: Irritação no TRS inferior. | K23: TC | M23: NIOSH 1606 | N23: Cromatografia | O23: 0,01 - 0,2 | P23: 3 - 25
A24: Ácido acético | B24: N. C. | C24: Ácido acético | D24: ppm | E24: Ácido acético | F24: 8,8 | G24: 13,2 | H24: 8 | I24: Ácido acético | J24: Irritação no TRS e olhos, comprometimento pulmonar. | K24: TC | M24: NIOSH 1603 | N24: Cromatografia | O24: 0,01 - 1 | P24: 15 - 300
A25: Ácido acetilsalicílico | B25: N. C. | C25: Ácido acetilsalicílico | D25: mg/m3 | E25: Ácido acetilsalicílico | F25: 4,4 | G25: - | H25: - | I25: Ácido acetilsalicílico | J25: Irritação na pele e olhos. | K25: K7 - | M25: NIOSH 0500 | N25: Gravimetria | O25: 1 - 2 | P25: 1 - 400
A26: Ácido acrílico | B26: N. C. | C26: Ácido acrílico | D26: ppm | E26: Ácido acrílico | F26: 1,76 | G26: - | H26: - | I26: Ácido acrílico | J26: Irritação no TRS. | K26: Tubo Anasorb | M26: OSHA 2005 | N26: Cromatografia | O26: ≤0,1 | P26: 1,5 - 24
A27: Ácido adípico | B27: N. C. | C27: Ácido adípico | D27: mg/m3 | E27: Ácido adípico | F27: 4,4 | G27: - | H27: - | I27: Ácido adípico | J27: Irritação no TRS; comprometimento no SNA. | K27: Tubo de XAD-2 | M27: OSHA SLTC In-House File | N27: Cromatografia | O27: 0.2 | P27: ≤100
A28: Ácido bromídrico | B28: N. C. | C28: Ácido bromídrico | D28: ppm | E28: Ácido bromídrico | F28: - | G28: 1,76 | H28: - | I28: Ácido bromídrico | J28: Irritação no TRS. | K28: K7 | M28: NIOSH 7907 | N28: Cromatografia | O28: 2 | P28: 30
A29: Ácido cianídrico | B29: N. C. | C29: Ácido cianídrico | D29: ppm | E29: Ácido cianídrico | F29: - | G29: 4.15 | H29: 8 | I29: Ácido cianídrico | J29: Irritação TRS; dor de cabeça; náusea; efe tireoide | K29: -
A30: Ácido clorídrico | B30: 02.09.031 | C30: Ácido clorídrico | D30: ppm | E30: Ácido clorídrico | F30: - | G30: 1.76 | H30: 4 | I30: Ácido clorídrico | J30: Irritação TRS | K30: TSG | M30: OSHA ID165-SG / OSHA ID-174-SG | N30: Cromatografia de Íons | O30: 0.5 | P30: 7,5
A31: Ácido 2-cloropropiônico | B31: N. C. | C31: Ácido 2-cloropropiônico | D31: ppm | E31: Ácido 2-cloropropiônico | F31: 0,088 | G31: - | H31: - | I31: Ácido 2-cloropropiônico | J31: Dano reprodutivo masculino | K31: -
A32: Ácido dicloroacético | B32: N. C. | C32: Ácido dicloroacético | D32: ppm | E32: Ácido dicloroacético | F32: 0,44 | G32: - | H32: - | I32: Ácido dicloroacético | J32: Irritação olhos e TRS; dano testicular | K32: -
A33: Ácido 2,2-dicloropropiônico | B33: N. C. | C33: Ácido 2,2-dicloropropiônico | D33: mg/m3 | E33: Ácido 2,2-dicloropropiônico | F33: 4,4 | G33: - | H33: - | I33: Ácido 2,2-dicloropropiônico | J33: Irritação olhos e TRS | K33: -
A34: Ácido 2-etil hexanoico | B34: N. C. | C34: Ácido 2-etil hexanoico | D34: mg/m3 | E34: Ácido 2-etil hexanoico | F34: 4,4 | G34: - | H34: - | I34: Ácido 2-etil hexanoico | J34: Efe teratogênico | K34: -
A35: Ácido fluorídrico | B35: N. C. | C35: Ácido fluorídrico | D35: ppm | E35: Ácido fluorídrico | F35: 0,44 | G35: 1,76 | H35: 2,5 | I35: Ácido fluorídrico | J35: Irritação TRS e TRI; Irritação olhos e pele; fluorose | K35: K7 | M35: NIOSH 7902 | N35: Íons Específicos | O35: 1 - 2 | P35: 1 - 120
A36: Ácido fórmico | B36: N. C. | C36: Ácido fórmico | D36: ppm | E36: Ácido fórmico | F36: 4,4 | G36: 8,8 | H36: 4 | I36: Ácido fórmico | J36: Irritação olhos, pele e TRS | K36: TSG | M36: NIOSH 2011 | N36: Cromatografia | O36: 0,05 - 0,2 | P36: 1 - 24
A37: Ácido fosfórico | B37: 02.12.003 | C37: Ácido fosfórico | D37: mg/m3 | E37: Ácido fosfórico | F37: 0.88 | G37: 2.64 | H37: - | I37: Ácido fosfórico | J37: Irritação olhos, pele e TRS | K37: TSG | M37: OSHA ID165-SG / OSHA ID-174-SG | N37: Cromatografia de Íons | O37: 0,2 L/ min | P37: 96L
A38: Ácido metacrílico | B38: N. C. | C38: Ácido metacrílico | D38: ppm | E38: Ácido metacrílico | F38: 17,6 | G38: - | H38: - | I38: Ácido metacrílico | J38: Irritação olhos e pele
A39: Ácido monocloroacético | B39: N. C. | C39: Ácido monocloroacético | D39: ppm | E39: Ácido monocloroacético | F39: 0,44 | G39: - | H39: - | I39: Ácido monocloroacético | J39: Irritação TRS
A40: Ácido nítrico | B40: N. C. | C40: Ácido nítrico | D40: ppm | E40: Ácido nítrico | F40: 1.76 | G40: 3.52 | H40: - | I40: Ácido nítrico | J40: Irritação olhos e TRS; corrosão dental | K40: TSG | M40: OSHA ID165-SG / OSHA ID-174-SG | N40: Cromatografia de Íons | O40: 0,2 L/ min | P40: 96L
A41: Ácido oxálico | B41: N. C. | C41: Ácido oxálico | D41: mg/m3 | E41: Ácido oxálico | F41: 0,88 | G41: 1,76 | H41: - | I41: Ácido oxálico | J41: Irritação olhos, pele e TRS | K41: K7 | M41: OSHA PV2115 | N41: Cromatografia de íons | O41: máxima de 1 L/min | P41: Recomendado volume máximo 100L
A42: Ácido peracético | B42: N. C. | C42: Ácido peracético | D42: ppm | E42: Ácido peracético | F42: - | G42: 0.35 | H42: - | I42: Ácido peracético | J42: Irritação olhos, pele e TRS | K42: TSG | M42: IT 10-220 | N42: Cromatografia Líquida de Alta Resoluçao com Detector de UV | O42: 1 L/min | P42: máxima de 30 L
A43: Ácido pícrico | B43: N. C. | C43: Ácido pícrico | D43: mg/m3 | E43: Ácido pícrico | F43: 0.08 | G43: - | H43: - | I43: Ácido pícrico | J43: Sens pele; dermatite; Irritação olhos
A44: Ácido propiônico | B44: N. C. | C44: Ácido propiônico | D44: ppm | E44: Ácido propiônico | F44: 8,8 | G44: - | H44: - | I44: Ácido propiônico | J44: Irritação olhos, pele e TRS
A45: Ácido Sulfúrico | B45: N. C. | C45: Ácido Sulfúrico | D45: mg/m3 | E45: Ácido Sulfúrico | F45: 0.18 | G45: - | H45: - | I45: Ácido Sulfúrico | J45: Função pulmonar | K45: k7 | M45: OSHA ID-113 modificado | N45: Cromatografia de Íons | O45: 1,6 L/min | P45: 480 L
A46: Ácido tereftálico | B46: N. C. | C46: Ácido tereftálico | D46: mg/m3 | E46: Ácido tereftálico | F46: 8,8 | G46: - | H46: - | I46: Ácido tereftálico | J46: -
A47: Ácido tioglicólico | B47: N. C. | C47: Ácido tioglicólico | D47: ppm | E47: Ácido tioglicólico | F47: 0,88 | G47: - | H47: - | I47: Ácido tioglicólico | J47: Irritação olhos e pele
A48: Ácido tricloroacético | B48: N. C. | C48: Ácido tricloroacético | D48: ppm | E48: Ácido tricloroacético | F48: 0,44 | G48: - | H48: - | I48: Ácido tricloroacético | J48: Irritação olhos e TRS
A49: Acrilamida | B49: N. C. | C49: Acrilamida | D49: mg/m3 | E49: Acrilamida | F49: 0.03 | G49: - | H49: - | I49: Acrilamida | J49: SNC compr
A50: Acrilato de n-butila | B50: N. C. | C50: Acrilato de n-butila | D50: ppm | E50: Acrilato de n-butila | F50: 1,76 | G50: - | H50: - | I50: Acrilato de n-butila | J50: Irritação
A51: Acrilato de etila | B51: N. C. | C51: Acrilato de etila | D51: ppm | E51: Acrilato de etila | F51: 4,4 | G51: 13,2 | H51: - | I51: Acrilato de etila | J51: Irritação olhos, TRS e GI; compr SNC; sem pele
A52: Acrilato de 2-hidroxipropila | B52: N. C. | C52: Acrilato de 2-hidroxipropila | D52: ppm | E52: Acrilato de 2-hidroxipropila | F52: 0,44 | G52: - | H52: - | I52: Acrilato de 2-hidroxipropila | J52: Irritação olhos e TRS
A53: Acrilato de metila | B53: N. C. | C53: Acrilato de metila | D53: ppm | E53: Acrilato de metila | F53: 1,76 | G53: - | H53: 8 | I53: Acrilato de metila | J53: Irritação olhos, pele e TRS; dano olhos
A54: Acrilonitrila | B54: N. C. | C54: Acrilonitrila | D54: ppm | E54: Acrilonitrila | F54: 1,76 | G54: - | H54: 16 | I54: Acrilonitrila | J54: Compr SNC; Irritação TRI
A55: Acroleína | B55: N. C. | C55: Acroleína | D55: ppm | E55: Acroleína | F55: - | G55: 0.08 | H55: - | I55: Acroleína | J55: Irritação TRS e olhos; edema pulm; enfisema pumonar
A56: Adiponitrila | B56: N. C. | C56: Adiponitrila | D56: ppm | E56: Adiponitrila | F56: 1,76 | G56: - | H56: - | I56: Adiponitrila | J56: Irritação TRS e TRI
A57: Aguarrás Mineral | B57: N. C. | C57: Aguarrás Mineral | D57: ppm | E57: Aguarrás Mineral | F57: 88 | G57: - | H57: - | I57: Aguarrás Mineral | J57: Dano olhos, pele e rins; náusea; compr SNC
A58: Alaclor | B58: N. C. | C58: Alaclor | D58: mg/m3 | E58: Alaclor | F58: 0,88 | G58: - | H58: - | I58: Alaclor | J58: Hemossiderose (fígado, baço e rins)
A59: Alcatrão de hulha | B59: N. C. | C59: Alcatrão de hulha | D59: mg/m3 | E59: Alcatrão de hulha | F59: 0,176 | G59: - | H59: - | I59: Alcatrão de hulha | J59: Câncer
A60: Álcool alílico | B60: N. C. | C60: Álcool alílico | D60: ppm | E60: Álcool alílico | F60: 0,44 | G60: - | H60: - | I60: Álcool alílico | J60: Irritação TRS e olhos
A61: Álcool Etílico | B61: N. C. | C61: Álcool Etílico | D61: ppm | E61: Álcool Etílico | F61: - | G61: 880 | H61: 780 | I61: Álcool Etílico | J61: Irritação TRS
A62: Álcool n-butílico | B62: N. C. | C62: Álcool n-butílico | D62: ppm | E62: Álcool n-butílico | F62: 17.6 | G62: - | H62: 40 | I62: Álcool n-butílico | J62: Irritação olhos e TRS | K62: TC | L62: n-butanol | M62: NIOSH 1401 | N62: Cromatografia | O62: 0,01 a 0,2 | P62: 1 a 10
A63: Álcool sec-butílico | B63: N. C. | C63: Álcool sec-butílico | D63: ppm | E63: Álcool sec-butílico | F63: 88 | G63: - | H63: 115 | I63: Álcool sec-butílico | J63: Irritação TRS; compr SNC
A64: Álcool terc-butílico | B64: N. C. | C64: Álcool terc-butílico | D64: ppm | E64: Álcool terc-butílico | F64: 88 | G64: - | H64: 78 | I64: Álcool terc-butílico | J64: Compr SNC
A65: Álcool furfurílico | B65: N. C. | C65: Álcool furfurílico | D65: ppm | E65: Álcool furfurílico | F65: 0.18 | G65: - | H65: 4 | I65: Álcool furfurílico | J65: Irritação olhos e TRS
A66: Álcool isoamílico | B66: N. C. | C66: Álcool isoamílico | D66: ppm | E66: Álcool isoamílico | F66: 88 | G66: 110 | H66: 78 | I66: Álcool isoamílico | J66: Irritação olhos e TRS
A67: Álcool isobutílico | B67: N. C. | C67: Álcool isobutílico | D67: ppm | E67: Álcool isobutílico | F67: 44 | G67: - | H67: 40 | I67: Álcool isobutílico | J67: Irritação olhos e pele | K67: TC | L67: Alcool Isobutanol | M67: NIOSH 1401 | N67: Cromatografia | O67: 0,01 a 0,2 | P67: 1 a 10
A68: Álcool isooctílico | B68: N. C. | C68: Álcool isooctílico | D68: ppm | E68: Álcool isooctílico | F68: 44 | G68: - | H68: - | I68: Álcool isooctílico | J68: Irritação TRS
A69: Álcool Isopropílico | B69: N. C. | C69: Álcool Isopropílico | D69: ppm | E69: Álcool Isopropílico | F69: 176 | G69: 352 | H69: 310 | I69: Álcool Isopropílico | J69: Irritação olhos e TRS; compr SNC | K69: TC | L69: Alcool Isopropanol | M69: NIOSH 1400 | N69: Cromatografia | O69: 0,01 a 0,2 | P69: 0,2 A 3
A70: Álcool propargílico | B70: N. C. | C70: Álcool propargílico | D70: ppm | E70: Álcool propargílico | F70: 0,88 | G70: - | H70: - | I70: Álcool propargílico | J70: Irritação olhos; dano fígado e rins
A71: Álcool n-propílico | B71: N. C. | C71: Álcool n-propílico | D71: ppm | E71: Álcool n-propílico | F71: 88 | G71: - | H71: 156 | I71: Álcool n-propílico | J71: Irritação olhos e TRS
A72: Aldrin | B72: N. C. | C72: Aldrin | D72: mg/m3 | E72: Aldrin | F72: 0.04 | G72: - | H72: - | I72: Aldrin | J72: Compr SNC; dano fígado e rins
A73: Algodão | B73: N. C. | C73: Algodão | D73: mg/m3 | E73: Algodão | F73: 0,088 | G73: - | H73: - | I73: Algodão | J73: Bissinose; bronquite; função pulmonar
A74: Alumínio metal | B74: N. C. | C74: Alumínio metal | D74: mg/m3 | E74: Alumínio metal | F74: 0,88 | G74: - | H74: - | I74: Alumínio metal | J74: Pneumoconiose; Irritação TRI neurotoxicidade
A75: Amido | B75: N. C. | C75: Amido | D75: mg/m3 | E75: Amido | F75: 8,8 | G75: - | H75: - | I75: Amido | J75: Dermatite
A76: 4-Aminodifenil | B76: N. C. | C76: 4-Aminodifenil | D76: - | E76: 4-Aminodifenil | F76: - | G76: - | H76: - | I76: 4-Aminodifenil | J76: Câncer de fígado e bexiga
A77: 2-Aminopiridina | B77: N. C. | C77: 2-Aminopiridina | D77: ppm | E77: 2-Aminopiridina | F77: 0,44 | G77: - | H77: - | I77: 2-Aminopiridina | J77: Dor de cabeça; náusea; compr SNC; tontura
A78: Amitrol | B78: N. C. | C78: Amitrol | D78: mg/m3 | E78: Amitrol | F78: 0,176 | G78: - | H78: - | I78: Amitrol | J78: efe tireoide
A79: Amônia | B79: N. C. | C79: Amônia | D79: ppm | E79: Amônia | F79: 22 | G79: 30.8 | H79: 20 | I79: Amônia | J79: Dano olhos; Irritação TRS | K79: K7 com MCE e TSG | M79: NIOSH 6016 | N79: Cromatografia de Íons | O79: 0,1 a 0,5 | P79: 3 a 96 L
A80: Anídrico acético | B80: N. C. | C80: Anídrico acético | D80: ppm | E80: Anídrico acético | F80: 0,88 | G80: 2,64 | H80: - | I80: Anídrico acético | J80: Irritação TRS e olhos
A81: Anidrido ftálico | B81: N. C. | C81: Anidrido ftálico | D81: mg/m3 | E81: Anidrido ftálico | F81: 0.00176 | G81: 0.0044 | H81: - | I81: Anidrido ftálico | J81: Irritação olhos, pele e TRS
A82: Anidrido hexahidroftálico | B82: N. C. | C82: Anidrido hexahidroftálico | D82: mg/m3 | E82: Anidrido hexahidroftálico | F82: - | G82: 0,0044 | H82: - | I82: Anidrido hexahidroftálico | J82: Sens
A83: Anidrido maleico | B83: N. C. | C83: Anidrido maleico | D83: ppm | E83: Anidrido maleico | F83: 0,0088 | G83: - | H83: - | I83: Anidrido maleico | J83: Resp sens
A84: Anidrido trimelítico | B84: N. C. | C84: Anidrido trimelítico | D84: mg/m3 | E84: Anidrido trimelítico | F84: 0,00044 | G84: 0,00176 | H84: - | I84: Anidrido trimelítico | J84: Sens resp
A85: Antimônio | B85: N. C. | C85: Antimônio | D85: mg/m3 | E85: Antimônio | F85: 0,44 | G85: - | H85: - | I85: Antimônio | J85: Irritação TRS e pele
A86: ANTU | B86: N. C. | C86: ANTU | D86: mg/m3 | E86: ANTU | F86: 0,264 | G86: - | H86: - | I86: ANTU | J86: Efe tireoide; náusea
A87: Arseneto de gálio | B87: N. C. | C87: Arseneto de gálio | D87: mg/m3 | E87: Arseneto de gálio | F87: 0,000264 | G87: - | H87: - | I87: Arseneto de gálio | J87: Irritação TRI
A88: Arsênio | B88: 02.01.001 | C88: Arsênio | D88: mg/m3 | E88: Arsênio | F88: 0,0088 | G88: - | H88: - | I88: Arsênio | J88: Câncer do pulmão
A89: Arsina | B89: 02.01.002 | C89: Arsina | D89: ppm | E89: Arsina | F89: 0,0044 | G89: - | H89: 0,04 | I89: Arsina | J89: Compr SNP e sistema vascular; compr fígado e rins
A90: Arbesto | B90: N. C. | C90: Arbesto | D90: f/cc | E90: Arbesto | F90: 0,088 | G90: - | H90: - | I90: Arbesto | J90: Pneumoconiose; câncer do pulmão; mesotlioma
A91: Asfalto | B91: N. C. | C91: Asfalto | D91: mg/m3 | E91: Asfalto | F91: 0,44 | G91: - | H91: - | I91: Asfalto | J91: Irritação TRS e olhos
A92: Atrazine | B92: N. C. | C92: Atrazine | D92: mg/m3 | E92: Atrazine | F92: 1,76 | G92: - | H92: - | I92: Atrazine | J92: Ef hematológico, reprodutivo, desenvol.
A93: Azida de sódio | B93: N. C. | C93: Azida de sódio | D93: mg/m3 | E93: Azida de sódio | F93: - | G93: 0,2552 | H93: - | I93: Azida de sódio | J93: Compr card; dano pulmão
... A96: Benomil | B96: N. C. | C96: Benomil | D96: mg/m3 | E96: Benomil | F96: 0,88 | G96: - | H96: - | I96: Benomil | J96: Irritação TRS. Dano reprod testicular e dano embrio / fetal
A97: Benzeno | B97: 02.03.001 | C97: Benzeno | D97: ppm | E97: Benzeno | F97: 0.44 | G97: 2.2 | H97: - | I97: Benzeno | J97: Leucemia | K97: tc | M97: NIOSH 1501 | N97: Cromatografia | O97: máx. 0,20 | P97: 3 - 30
A98: Benzidina | B98: N. C. | C98: Benzidina | D98: - | E98: Benzidina | F98: - | G98: - | H98: - | I98: Benzidina | J98: Câncer de bexiga
A99: Benzo[a]antraceno | B99: N. C. | C99: Benzo[a]antraceno | D99: - | E99: Benzo[a]antraceno | F99: - | G99: - | H99: - | I99: Benzo[a]antraceno | J99: Câncer de pele
A100: Benzo[b]fluoranteno | B100: N. C. | C100: Benzo[b]fluoranteno | D100: - | E100: Benzo[b]fluoranteno | F100: - | G100: - | H100: - | I100: Benzo[b]fluoranteno | J100: Câncer
A101: Benzo[a]pireno | B101: N. C. | C101: Benzo[a]pireno | D101: - | E101: Benzo[a]pireno | F101: - | G101: - | H101: - | I101: Benzo[a]pireno | J101: Câncer
A102: Berílio | B102: 02.04.001 | C102: Berílio | D102: mg/m3 | E102: Berílio | F102: 0,000044 | G102: - | H102: - | I102: Berílio | J102: Sens Berílio; doença crônica do berílio (berilose)
...
